{
  "regions": {
    "ap-south-2": {
      "nodejs16.x": "arn:aws:lambda:ap-south-2:464622532012:layer:Datadog-Node16-x:120",
      "nodejs18.x": "arn:aws:lambda:ap-south-2:464622532012:layer:Datadog-Node18-x:132",
      "nodejs20.x": "arn:aws:lambda:ap-south-2:464622532012:layer:Datadog-Node20-x:132",
      "nodejs22.x": "arn:aws:lambda:ap-south-2:464622532012:layer:Datadog-Node22-x:132",
      "nodejs24.x": "arn:aws:lambda:ap-south-2:464622532012:layer:Datadog-Node24-x:132",
      "python3.7": "arn:aws:lambda:ap-south-2:464622532012:layer:Datadog-Python37:85",
      "python3.8": "arn:aws:lambda:ap-south-2:464622532012:layer:Datadog-Python38:120",
      "python3.8-arm": "arn:aws:lambda:ap-south-2:464622532012:layer:Datadog-Python38-ARM:120",
      "python3.9": "arn:aws:lambda:ap-south-2:464622532012:layer:Datadog-Python39:120",
      "python3.9-arm": "arn:aws:lambda:ap-south-2:464622532012:layer:Datadog-Python39-ARM:120",
      "python3.10": "arn:aws:lambda:ap-south-2:464622532012:layer:Datadog-Python310:120",
      "python3.10-arm": "arn:aws:lambda:ap-south-2:464622532012:layer:Datadog-Python310-ARM:120",
      "python3.11": "arn:aws:lambda:ap-south-2:464622532012:layer:Datadog-Python311:120",
      "python3.11-arm": "arn:aws:lambda:ap-south-2:464622532012:layer:Datadog-Python311-ARM:120",
      "python3.12": "arn:aws:lambda:ap-south-2:464622532012:layer:Datadog-Python312:120",
      "python3.12-arm": "arn:aws:lambda:ap-south-2:464622532012:layer:Datadog-Python312-ARM:120",
      "python3.13": "arn:aws:lambda:ap-south-2:464622532012:layer:Datadog-Python313:120",
      "python3.13-arm": "arn:aws:lambda:ap-south-2:464622532012:layer:Datadog-Python313-ARM:120",
      "python3.14": "arn:aws:lambda:ap-south-2:464622532012:layer:Datadog-Python314:120",
      "python3.14-arm": "arn:aws:lambda:ap-south-2:464622532012:layer:Datadog-Python314-ARM:120",
      "ruby3.2": "arn:aws:lambda:ap-south-2:464622532012:layer:Datadog-Ruby3-2:27",
      "ruby3.2-arm": "arn:aws:lambda:ap-south-2:464622532012:layer:Datadog-Ruby3-2-ARM:27",
      "ruby3.3": "arn:aws:lambda:ap-south-2:464622532012:layer:Datadog-Ruby3-3:27",
      "ruby3.3-arm": "arn:aws:lambda:ap-south-2:464622532012:layer:Datadog-Ruby3-3-ARM:27",
      "ruby3.4": "arn:aws:lambda:ap-south-2:464622532012:layer:Datadog-Ruby3-4:27",
      "ruby3.4-arm": "arn:aws:lambda:ap-south-2:464622532012:layer:Datadog-Ruby3-4-ARM:27",
      "extension": "arn:aws:lambda:ap-south-2:464622532012:layer:Datadog-Extension:91",
      "extension-arm": "arn:aws:lambda:ap-south-2:464622532012:layer:Datadog-Extension-ARM:91",
      "extension-fips": "arn:aws:lambda:ap-south-2:464622532012:layer:Datadog-Extension-FIPS:91",
      "extension-arm-fips": "arn:aws:lambda:ap-south-2:464622532012:layer:Datadog-Extension-ARM-FIPS:91",
      "dotnet": "arn:aws:lambda:ap-south-2:464622532012:layer:dd-trace-dotnet:23",
      "dotnet-arm": "arn:aws:lambda:ap-south-2:464622532012:layer:dd-trace-dotnet-ARM:23",
      "java": "arn:aws:lambda:ap-south-2:464622532012:layer:dd-trace-java:25"
    },
    "ap-south-1": {
      "nodejs16.x": "arn:aws:lambda:ap-south-1:464622532012:layer:Datadog-Node16-x:120",
      "nodejs18.x": "arn:aws:lambda:ap-south-1:464622532012:layer:Datadog-Node18-x:132",
      "nodejs20.x": "arn:aws:lambda:ap-south-1:464622532012:layer:Datadog-Node20-x:132",
      "nodejs22.x": "arn:aws:lambda:ap-south-1:464622532012:layer:Datadog-Node22-x:132",
      "nodejs24.x": "arn:aws:lambda:ap-south-1:464622532012:layer:Datadog-Node24-x:132",
      "python3.7": "arn:aws:lambda:ap-south-1:464622532012:layer:Datadog-Python37:85",
      "python3.8": "arn:aws:lambda:ap-south-1:464622532012:layer:Datadog-Python38:120",
      "python3.8-arm": "arn:aws:lambda:ap-south-1:464622532012:layer:Datadog-Python38-ARM:120",
      "python3.9": "arn:aws:lambda:ap-south-1:464622532012:layer:Datadog-Python39:120",
      "python3.9-arm": "arn:aws:lambda:ap-south-1:464622532012:layer:Datadog-Python39-ARM:120",
      "python3.10": "arn:aws:lambda:ap-south-1:464622532012:layer:Datadog-Python310:120",
      "python3.10-arm": "arn:aws:lambda:ap-south-1:464622532012:layer:Datadog-Python310-ARM:120",
      "python3.11": "arn:aws:lambda:ap-south-1:464622532012:layer:Datadog-Python311:120",
      "python3.11-arm": "arn:aws:lambda:ap-south-1:464622532012:layer:Datadog-Python311-ARM:120",
      "python3.12": "arn:aws:lambda:ap-south-1:464622532012:layer:Datadog-Python312:120",
      "python3.12-arm": "arn:aws:lambda:ap-south-1:464622532012:layer:Datadog-Python312-ARM:120",
      "python3.13": "arn:aws:lambda:ap-south-1:464622532012:layer:Datadog-Python313:120",
      "python3.13-arm": "arn:aws:lambda:ap-south-1:464622532012:layer:Datadog-Python313-ARM:120",
      "python3.14": "arn:aws:lambda:ap-south-1:464622532012:layer:Datadog-Python314:120",
      "python3.14-arm": "arn:aws:lambda:ap-south-1:464622532012:layer:Datadog-Python314-ARM:120",
      "ruby3.2": "arn:aws:lambda:ap-south-1:464622532012:layer:Datadog-Ruby3-2:27",
      "ruby3.2-arm": "arn:aws:lambda:ap-south-1:464622532012:layer:Datadog-Ruby3-2-ARM:27",
      "ruby3.3": "arn:aws:lambda:ap-south-1:464622532012:layer:Datadog-Ruby3-3:27",
      "ruby3.3-arm": "arn:aws:lambda:ap-south-1:464622532012:layer:Datadog-Ruby3-3-ARM:27",
      "ruby3.4": "arn:aws:lambda:ap-south-1:464622532012:layer:Datadog-Ruby3-4:27",
      "ruby3.4-arm": "arn:aws:lambda:ap-south-1:464622532012:layer:Datadog-Ruby3-4-ARM:27",
      "extension": "arn:aws:lambda:ap-south-1:464622532012:layer:Datadog-Extension:91",
      "extension-arm": "arn:aws:lambda:ap-south-1:464622532012:layer:Datadog-Extension-ARM:91",
      "extension-fips": "arn:aws:lambda:ap-south-1:464622532012:layer:Datadog-Extension-FIPS:91",
      "extension-arm-fips": "arn:aws:lambda:ap-south-1:464622532012:layer:Datadog-Extension-ARM-FIPS:91",
      "dotnet": "arn:aws:lambda:ap-south-1:464622532012:layer:dd-trace-dotnet:23",
      "dotnet-arm": "arn:aws:lambda:ap-south-1:464622532012:layer:dd-trace-dotnet-ARM:23",
      "java": "arn:aws:lambda:ap-south-1:464622532012:layer:dd-trace-java:25"
    },
    "eu-south-1": {
      "nodejs16.x": "arn:aws:lambda:eu-south-1:464622532012:layer:Datadog-Node16-x:120",
      "nodejs18.x": "arn:aws:lambda:eu-south-1:464622532012:layer:Datadog-Node18-x:132",
      "nodejs20.x": "arn:aws:lambda:eu-south-1:464622532012:layer:Datadog-Node20-x:132",
      "nodejs22.x": "arn:aws:lambda:eu-south-1:464622532012:layer:Datadog-Node22-x:132",
      "nodejs24.x": "arn:aws:lambda:eu-south-1:464622532012:layer:Datadog-Node24-x:132",
      "python3.7": "arn:aws:lambda:eu-south-1:464622532012:layer:Datadog-Python37:85",
      "python3.8": "arn:aws:lambda:eu-south-1:464622532012:layer:Datadog-Python38:120",
      "python3.8-arm": "arn:aws:lambda:eu-south-1:464622532012:layer:Datadog-Python38-ARM:120",
      "python3.9": "arn:aws:lambda:eu-south-1:464622532012:layer:Datadog-Python39:120",
      "python3.9-arm": "arn:aws:lambda:eu-south-1:464622532012:layer:Datadog-Python39-ARM:120",
      "python3.10": "arn:aws:lambda:eu-south-1:464622532012:layer:Datadog-Python310:120",
      "python3.10-arm": "arn:aws:lambda:eu-south-1:464622532012:layer:Datadog-Python310-ARM:120",
      "python3.11": "arn:aws:lambda:eu-south-1:464622532012:layer:Datadog-Python311:120",
      "python3.11-arm": "arn:aws:lambda:eu-south-1:464622532012:layer:Datadog-Python311-ARM:120",
      "python3.12": "arn:aws:lambda:eu-south-1:464622532012:layer:Datadog-Python312:120",
      "python3.12-arm": "arn:aws:lambda:eu-south-1:464622532012:layer:Datadog-Python312-ARM:120",
      "python3.13": "arn:aws:lambda:eu-south-1:464622532012:layer:Datadog-Python313:120",
      "python3.13-arm": "arn:aws:lambda:eu-south-1:464622532012:layer:Datadog-Python313-ARM:120",
      "python3.14": "arn:aws:lambda:eu-south-1:464622532012:layer:Datadog-Python314:120",
      "python3.14-arm": "arn:aws:lambda:eu-south-1:464622532012:layer:Datadog-Python314-ARM:120",
      "ruby3.2": "arn:aws:lambda:eu-south-1:464622532012:layer:Datadog-Ruby3-2:27",
      "ruby3.2-arm": "arn:aws:lambda:eu-south-1:464622532012:layer:Datadog-Ruby3-2-ARM:27",
      "ruby3.3": "arn:aws:lambda:eu-south-1:464622532012:layer:Datadog-Ruby3-3:27",
      "ruby3.3-arm": "arn:aws:lambda:eu-south-1:464622532012:layer:Datadog-Ruby3-3-ARM:27",
      "ruby3.4": "arn:aws:lambda:eu-south-1:464622532012:layer:Datadog-Ruby3-4:27",
      "ruby3.4-arm": "arn:aws:lambda:eu-south-1:464622532012:layer:Datadog-Ruby3-4-ARM:27",
      "extension": "arn:aws:lambda:eu-south-1:464622532012:layer:Datadog-Extension:91",
      "extension-arm": "arn:aws:lambda:eu-south-1:464622532012:layer:Datadog-Extension-ARM:91",
      "extension-fips": "arn:aws:lambda:eu-south-1:464622532012:layer:Datadog-Extension-FIPS:91",
      "extension-arm-fips": "arn:aws:lambda:eu-south-1:464622532012:layer:Datadog-Extension-ARM-FIPS:91",
      "dotnet": "arn:aws:lambda:eu-south-1:464622532012:layer:dd-trace-dotnet:23",
      "dotnet-arm": "arn:aws:lambda:eu-south-1:464622532012:layer:dd-trace-dotnet-ARM:23",
      "java": "arn:aws:lambda:eu-south-1:464622532012:layer:dd-trace-java:25"
    },
    "eu-south-2": {
      "nodejs16.x": "arn:aws:lambda:eu-south-2:464622532012:layer:Datadog-Node16-x:120",
      "nodejs18.x": "arn:aws:lambda:eu-south-2:464622532012:layer:Datadog-Node18-x:132",
      "nodejs20.x": "arn:aws:lambda:eu-south-2:464622532012:layer:Datadog-Node20-x:132",
      "nodejs22.x": "arn:aws:lambda:eu-south-2:464622532012:layer:Datadog-Node22-x:132",
      "nodejs24.x": "arn:aws:lambda:eu-south-2:464622532012:layer:Datadog-Node24-x:132",
      "python3.7": "arn:aws:lambda:eu-south-2:464622532012:layer:Datadog-Python37:85",
      "python3.8": "arn:aws:lambda:eu-south-2:464622532012:layer:Datadog-Python38:120",
      "python3.8-arm": "arn:aws:lambda:eu-south-2:464622532012:layer:Datadog-Python38-ARM:120",
      "python3.9": "arn:aws:lambda:eu-south-2:464622532012:layer:Datadog-Python39:120",
      "python3.9-arm": "arn:aws:lambda:eu-south-2:464622532012:layer:Datadog-Python39-ARM:120",
      "python3.10": "arn:aws:lambda:eu-south-2:464622532012:layer:Datadog-Python310:120",
      "python3.10-arm": "arn:aws:lambda:eu-south-2:464622532012:layer:Datadog-Python310-ARM:120",
      "python3.11": "arn:aws:lambda:eu-south-2:464622532012:layer:Datadog-Python311:120",
      "python3.11-arm": "arn:aws:lambda:eu-south-2:464622532012:layer:Datadog-Python311-ARM:120",
      "python3.12": "arn:aws:lambda:eu-south-2:464622532012:layer:Datadog-Python312:120",
      "python3.12-arm": "arn:aws:lambda:eu-south-2:464622532012:layer:Datadog-Python312-ARM:120",
      "python3.13": "arn:aws:lambda:eu-south-2:464622532012:layer:Datadog-Python313:120",
      "python3.13-arm": "arn:aws:lambda:eu-south-2:464622532012:layer:Datadog-Python313-ARM:120",
      "python3.14": "arn:aws:lambda:eu-south-2:464622532012:layer:Datadog-Python314:120",
      "python3.14-arm": "arn:aws:lambda:eu-south-2:464622532012:layer:Datadog-Python314-ARM:120",
      "ruby3.2": "arn:aws:lambda:eu-south-2:464622532012:layer:Datadog-Ruby3-2:27",
      "ruby3.2-arm": "arn:aws:lambda:eu-south-2:464622532012:layer:Datadog-Ruby3-2-ARM:27",
      "ruby3.3": "arn:aws:lambda:eu-south-2:464622532012:layer:Datadog-Ruby3-3:27",
      "ruby3.3-arm": "arn:aws:lambda:eu-south-2:464622532012:layer:Datadog-Ruby3-3-ARM:27",
      "ruby3.4": "arn:aws:lambda:eu-south-2:464622532012:layer:Datadog-Ruby3-4:27",
      "ruby3.4-arm": "arn:aws:lambda:eu-south-2:464622532012:layer:Datadog-Ruby3-4-ARM:27",
      "extension": "arn:aws:lambda:eu-south-2:464622532012:layer:Datadog-Extension:91",
      "extension-arm": "arn:aws:lambda:eu-south-2:464622532012:layer:Datadog-Extension-ARM:91",
      "extension-fips": "arn:aws:lambda:eu-south-2:464622532012:layer:Datadog-Extension-FIPS:91",
      "extension-arm-fips": "arn:aws:lambda:eu-south-2:464622532012:layer:Datadog-Extension-ARM-FIPS:91",
      "dotnet": "arn:aws:lambda:eu-south-2:464622532012:layer:dd-trace-dotnet:23",
      "dotnet-arm": "arn:aws:lambda:eu-south-2:464622532012:layer:dd-trace-dotnet-ARM:23",
      "java": "arn:aws:lambda:eu-south-2:464622532012:layer:dd-trace-java:25"
    },
    "me-central-1": {
      "nodejs16.x": "arn:aws:lambda:me-central-1:464622532012:layer:Datadog-Node16-x:120",
      "nodejs18.x": "arn:aws:lambda:me-central-1:464622532012:layer:Datadog-Node18-x:132",
      "nodejs20.x": "arn:aws:lambda:me-central-1:464622532012:layer:Datadog-Node20-x:132",
      "nodejs22.x": "arn:aws:lambda:me-central-1:464622532012:layer:Datadog-Node22-x:132",
      "nodejs24.x": "arn:aws:lambda:me-central-1:464622532012:layer:Datadog-Node24-x:132",
      "python3.7": "arn:aws:lambda:me-central-1:464622532012:layer:Datadog-Python37:85",
      "python3.8": "arn:aws:lambda:me-central-1:464622532012:layer:Datadog-Python38:120",
      "python3.8-arm": "arn:aws:lambda:me-central-1:464622532012:layer:Datadog-Python38-ARM:120",
      "python3.9": "arn:aws:lambda:me-central-1:464622532012:layer:Datadog-Python39:120",
      "python3.9-arm": "arn:aws:lambda:me-central-1:464622532012:layer:Datadog-Python39-ARM:120",
      "python3.10": "arn:aws:lambda:me-central-1:464622532012:layer:Datadog-Python310:120",
      "python3.10-arm": "arn:aws:lambda:me-central-1:464622532012:layer:Datadog-Python310-ARM:120",
      "python3.11": "arn:aws:lambda:me-central-1:464622532012:layer:Datadog-Python311:120",
      "python3.11-arm": "arn:aws:lambda:me-central-1:464622532012:layer:Datadog-Python311-ARM:120",
      "python3.12": "arn:aws:lambda:me-central-1:464622532012:layer:Datadog-Python312:120",
      "python3.12-arm": "arn:aws:lambda:me-central-1:464622532012:layer:Datadog-Python312-ARM:120",
      "python3.13": "arn:aws:lambda:me-central-1:464622532012:layer:Datadog-Python313:120",
      "python3.13-arm": "arn:aws:lambda:me-central-1:464622532012:layer:Datadog-Python313-ARM:120",
      "python3.14": "arn:aws:lambda:me-central-1:464622532012:layer:Datadog-Python314:120",
      "python3.14-arm": "arn:aws:lambda:me-central-1:464622532012:layer:Datadog-Python314-ARM:120",
      "ruby3.2": "arn:aws:lambda:me-central-1:464622532012:layer:Datadog-Ruby3-2:27",
      "ruby3.2-arm": "arn:aws:lambda:me-central-1:464622532012:layer:Datadog-Ruby3-2-ARM:27",
      "ruby3.3": "arn:aws:lambda:me-central-1:464622532012:layer:Datadog-Ruby3-3:27",
      "ruby3.3-arm": "arn:aws:lambda:me-central-1:464622532012:layer:Datadog-Ruby3-3-ARM:27",
      "ruby3.4": "arn:aws:lambda:me-central-1:464622532012:layer:Datadog-Ruby3-4:27",
      "ruby3.4-arm": "arn:aws:lambda:me-central-1:464622532012:layer:Datadog-Ruby3-4-ARM:27",
      "extension": "arn:aws:lambda:me-central-1:464622532012:layer:Datadog-Extension:91",
      "extension-arm": "arn:aws:lambda:me-central-1:464622532012:layer:Datadog-Extension-ARM:91",
      "extension-fips": "arn:aws:lambda:me-central-1:464622532012:layer:Datadog-Extension-FIPS:91",
      "extension-arm-fips": "arn:aws:lambda:me-central-1:464622532012:layer:Datadog-Extension-ARM-FIPS:91",
      "dotnet": "arn:aws:lambda:me-central-1:464622532012:layer:dd-trace-dotnet:23",
      "dotnet-arm": "arn:aws:lambda:me-central-1:464622532012:layer:dd-trace-dotnet-ARM:23",
      "java": "arn:aws:lambda:me-central-1:464622532012:layer:dd-trace-java:25"
    },
    "il-central-1": {
      "nodejs16.x": "arn:aws:lambda:il-central-1:464622532012:layer:Datadog-Node16-x:120",
      "nodejs18.x": "arn:aws:lambda:il-central-1:464622532012:layer:Datadog-Node18-x:132",
      "nodejs20.x": "arn:aws:lambda:il-central-1:464622532012:layer:Datadog-Node20-x:132",
      "nodejs22.x": "arn:aws:lambda:il-central-1:464622532012:layer:Datadog-Node22-x:132",
      "nodejs24.x": "arn:aws:lambda:il-central-1:464622532012:layer:Datadog-Node24-x:132",
      "python3.8": "arn:aws:lambda:il-central-1:464622532012:layer:Datadog-Python38:120",
      "python3.8-arm": "arn:aws:lambda:il-central-1:464622532012:layer:Datadog-Python38-ARM:120",
      "python3.9": "arn:aws:lambda:il-central-1:464622532012:layer:Datadog-Python39:120",
      "python3.9-arm": "arn:aws:lambda:il-central-1:464622532012:layer:Datadog-Python39-ARM:120",
      "python3.10": "arn:aws:lambda:il-central-1:464622532012:layer:Datadog-Python310:120",
      "python3.10-arm": "arn:aws:lambda:il-central-1:464622532012:layer:Datadog-Python310-ARM:120",
      "python3.11": "arn:aws:lambda:il-central-1:464622532012:layer:Datadog-Python311:120",
      "python3.11-arm": "arn:aws:lambda:il-central-1:464622532012:layer:Datadog-Python311-ARM:120",
      "python3.12": "arn:aws:lambda:il-central-1:464622532012:layer:Datadog-Python312:120",
      "python3.12-arm": "arn:aws:lambda:il-central-1:464622532012:layer:Datadog-Python312-ARM:120",
      "python3.13": "arn:aws:lambda:il-central-1:464622532012:layer:Datadog-Python313:120",
      "python3.13-arm": "arn:aws:lambda:il-central-1:464622532012:layer:Datadog-Python313-ARM:120",
      "python3.14": "arn:aws:lambda:il-central-1:464622532012:layer:Datadog-Python314:120",
      "python3.14-arm": "arn:aws:lambda:il-central-1:464622532012:layer:Datadog-Python314-ARM:120",
      "ruby3.2": "arn:aws:lambda:il-central-1:464622532012:layer:Datadog-Ruby3-2:27",
      "ruby3.2-arm": "arn:aws:lambda:il-central-1:464622532012:layer:Datadog-Ruby3-2-ARM:27",
      "ruby3.3": "arn:aws:lambda:il-central-1:464622532012:layer:Datadog-Ruby3-3:27",
      "ruby3.3-arm": "arn:aws:lambda:il-central-1:464622532012:layer:Datadog-Ruby3-3-ARM:27",
      "ruby3.4": "arn:aws:lambda:il-central-1:464622532012:layer:Datadog-Ruby3-4:27",
      "ruby3.4-arm": "arn:aws:lambda:il-central-1:464622532012:layer:Datadog-Ruby3-4-ARM:27",
      "extension": "arn:aws:lambda:il-central-1:464622532012:layer:Datadog-Extension:91",
      "extension-arm": "arn:aws:lambda:il-central-1:464622532012:layer:Datadog-Extension-ARM:91",
      "extension-fips": "arn:aws:lambda:il-central-1:464622532012:layer:Datadog-Extension-FIPS:91",
      "extension-arm-fips": "arn:aws:lambda:il-central-1:464622532012:layer:Datadog-Extension-ARM-FIPS:91",
      "dotnet": "arn:aws:lambda:il-central-1:464622532012:layer:dd-trace-dotnet:23",
      "dotnet-arm": "arn:aws:lambda:il-central-1:464622532012:layer:dd-trace-dotnet-ARM:23",
      "java": "arn:aws:lambda:il-central-1:464622532012:layer:dd-trace-java:25"
    },
    "ca-central-1": {
      "nodejs16.x": "arn:aws:lambda:ca-central-1:464622532012:layer:Datadog-Node16-x:120",
      "nodejs18.x": "arn:aws:lambda:ca-central-1:464622532012:layer:Datadog-Node18-x:132",
      "nodejs20.x": "arn:aws:lambda:ca-central-1:464622532012:layer:Datadog-Node20-x:132",
      "nodejs22.x": "arn:aws:lambda:ca-central-1:464622532012:layer:Datadog-Node22-x:132",
      "nodejs24.x": "arn:aws:lambda:ca-central-1:464622532012:layer:Datadog-Node24-x:132",
      "python3.7": "arn:aws:lambda:ca-central-1:464622532012:layer:Datadog-Python37:85",
      "python3.8": "arn:aws:lambda:ca-central-1:464622532012:layer:Datadog-Python38:120",
      "python3.8-arm": "arn:aws:lambda:ca-central-1:464622532012:layer:Datadog-Python38-ARM:120",
      "python3.9": "arn:aws:lambda:ca-central-1:464622532012:layer:Datadog-Python39:120",
      "python3.9-arm": "arn:aws:lambda:ca-central-1:464622532012:layer:Datadog-Python39-ARM:120",
      "python3.10": "arn:aws:lambda:ca-central-1:464622532012:layer:Datadog-Python310:120",
      "python3.10-arm": "arn:aws:lambda:ca-central-1:464622532012:layer:Datadog-Python310-ARM:120",
      "python3.11": "arn:aws:lambda:ca-central-1:464622532012:layer:Datadog-Python311:120",
      "python3.11-arm": "arn:aws:lambda:ca-central-1:464622532012:layer:Datadog-Python311-ARM:120",
      "python3.12": "arn:aws:lambda:ca-central-1:464622532012:layer:Datadog-Python312:120",
      "python3.12-arm": "arn:aws:lambda:ca-central-1:464622532012:layer:Datadog-Python312-ARM:120",
      "python3.13": "arn:aws:lambda:ca-central-1:464622532012:layer:Datadog-Python313:120",
      "python3.13-arm": "arn:aws:lambda:ca-central-1:464622532012:layer:Datadog-Python313-ARM:120",
      "python3.14": "arn:aws:lambda:ca-central-1:464622532012:layer:Datadog-Python314:120",
      "python3.14-arm": "arn:aws:lambda:ca-central-1:464622532012:layer:Datadog-Python314-ARM:120",
      "ruby3.2": "arn:aws:lambda:ca-central-1:464622532012:layer:Datadog-Ruby3-2:27",
      "ruby3.2-arm": "arn:aws:lambda:ca-central-1:464622532012:layer:Datadog-Ruby3-2-ARM:27",
      "ruby3.3": "arn:aws:lambda:ca-central-1:464622532012:layer:Datadog-Ruby3-3:27",
      "ruby3.3-arm": "arn:aws:lambda:ca-central-1:464622532012:layer:Datadog-Ruby3-3-ARM:27",
      "ruby3.4": "arn:aws:lambda:ca-central-1:464622532012:layer:Datadog-Ruby3-4:27",
      "ruby3.4-arm": "arn:aws:lambda:ca-central-1:464622532012:layer:Datadog-Ruby3-4-ARM:27",
      "extension": "arn:aws:lambda:ca-central-1:464622532012:layer:Datadog-Extension:91",
      "extension-arm": "arn:aws:lambda:ca-central-1:464622532012:layer:Datadog-Extension-ARM:91",
      "extension-fips": "arn:aws:lambda:ca-central-1:464622532012:layer:Datadog-Extension-FIPS:91",
      "extension-arm-fips": "arn:aws:lambda:ca-central-1:464622532012:layer:Datadog-Extension-ARM-FIPS:91",
      "dotnet": "arn:aws:lambda:ca-central-1:464622532012:layer:dd-trace-dotnet:23",
      "dotnet-arm": "arn:aws:lambda:ca-central-1:464622532012:layer:dd-trace-dotnet-ARM:23",
      "java": "arn:aws:lambda:ca-central-1:464622532012:layer:dd-trace-java:25"
    },
    "mx-central-1": {
      "nodejs18.x": "arn:aws:lambda:mx-central-1:464622532012:layer:Datadog-Node18-x:132",
      "nodejs20.x": "arn:aws:lambda:mx-central-1:464622532012:layer:Datadog-Node20-x:132",
      "nodejs22.x": "arn:aws:lambda:mx-central-1:464622532012:layer:Datadog-Node22-x:132",
      "nodejs24.x": "arn:aws:lambda:mx-central-1:464622532012:layer:Datadog-Node24-x:132",
      "python3.8": "arn:aws:lambda:mx-central-1:464622532012:layer:Datadog-Python38:120",
      "python3.8-arm": "arn:aws:lambda:mx-central-1:464622532012:layer:Datadog-Python38-ARM:120",
      "python3.9": "arn:aws:lambda:mx-central-1:464622532012:layer:Datadog-Python39:120",
      "python3.9-arm": "arn:aws:lambda:mx-central-1:464622532012:layer:Datadog-Python39-ARM:120",
      "python3.10": "arn:aws:lambda:mx-central-1:464622532012:layer:Datadog-Python310:120",
      "python3.10-arm": "arn:aws:lambda:mx-central-1:464622532012:layer:Datadog-Python310-ARM:120",
      "python3.11": "arn:aws:lambda:mx-central-1:464622532012:layer:Datadog-Python311:120",
      "python3.11-arm": "arn:aws:lambda:mx-central-1:464622532012:layer:Datadog-Python311-ARM:120",
      "python3.12": "arn:aws:lambda:mx-central-1:464622532012:layer:Datadog-Python312:120",
      "python3.12-arm": "arn:aws:lambda:mx-central-1:464622532012:layer:Datadog-Python312-ARM:120",
      "python3.13": "arn:aws:lambda:mx-central-1:464622532012:layer:Datadog-Python313:120",
      "python3.13-arm": "arn:aws:lambda:mx-central-1:464622532012:layer:Datadog-Python313-ARM:120",
      "python3.14": "arn:aws:lambda:mx-central-1:464622532012:layer:Datadog-Python314:120",
      "python3.14-arm": "arn:aws:lambda:mx-central-1:464622532012:layer:Datadog-Python314-ARM:120",
      "ruby3.2": "arn:aws:lambda:mx-central-1:464622532012:layer:Datadog-Ruby3-2:27",
      "ruby3.2-arm": "arn:aws:lambda:mx-central-1:464622532012:layer:Datadog-Ruby3-2-ARM:27",
      "ruby3.3": "arn:aws:lambda:mx-central-1:464622532012:layer:Datadog-Ruby3-3:27",
      "ruby3.3-arm": "arn:aws:lambda:mx-central-1:464622532012:layer:Datadog-Ruby3-3-ARM:27",
      "ruby3.4": "arn:aws:lambda:mx-central-1:464622532012:layer:Datadog-Ruby3-4:27",
      "ruby3.4-arm": "arn:aws:lambda:mx-central-1:464622532012:layer:Datadog-Ruby3-4-ARM:27",
      "extension": "arn:aws:lambda:mx-central-1:464622532012:layer:Datadog-Extension:91",
      "extension-arm": "arn:aws:lambda:mx-central-1:464622532012:layer:Datadog-Extension-ARM:91",
      "extension-fips": "arn:aws:lambda:mx-central-1:464622532012:layer:Datadog-Extension-FIPS:91",
      "extension-arm-fips": "arn:aws:lambda:mx-central-1:464622532012:layer:Datadog-Extension-ARM-FIPS:91",
      "dotnet": "arn:aws:lambda:mx-central-1:464622532012:layer:dd-trace-dotnet:23",
      "dotnet-arm": "arn:aws:lambda:mx-central-1:464622532012:layer:dd-trace-dotnet-ARM:23",
      "java": "arn:aws:lambda:mx-central-1:464622532012:layer:dd-trace-java:25"
    },
    "eu-central-1": {
      "nodejs16.x": "arn:aws:lambda:eu-central-1:464622532012:layer:Datadog-Node16-x:120",
      "nodejs18.x": "arn:aws:lambda:eu-central-1:464622532012:layer:Datadog-Node18-x:132",
      "nodejs20.x": "arn:aws:lambda:eu-central-1:464622532012:layer:Datadog-Node20-x:132",
      "nodejs22.x": "arn:aws:lambda:eu-central-1:464622532012:layer:Datadog-Node22-x:132",
      "nodejs24.x": "arn:aws:lambda:eu-central-1:464622532012:layer:Datadog-Node24-x:132",
      "python3.7": "arn:aws:lambda:eu-central-1:464622532012:layer:Datadog-Python37:85",
      "python3.8": "arn:aws:lambda:eu-central-1:464622532012:layer:Datadog-Python38:120",
      "python3.8-arm": "arn:aws:lambda:eu-central-1:464622532012:layer:Datadog-Python38-ARM:120",
      "python3.9": "arn:aws:lambda:eu-central-1:464622532012:layer:Datadog-Python39:120",
      "python3.9-arm": "arn:aws:lambda:eu-central-1:464622532012:layer:Datadog-Python39-ARM:120",
      "python3.10": "arn:aws:lambda:eu-central-1:464622532012:layer:Datadog-Python310:120",
      "python3.10-arm": "arn:aws:lambda:eu-central-1:464622532012:layer:Datadog-Python310-ARM:120",
      "python3.11": "arn:aws:lambda:eu-central-1:464622532012:layer:Datadog-Python311:120",
      "python3.11-arm": "arn:aws:lambda:eu-central-1:464622532012:layer:Datadog-Python311-ARM:120",
      "python3.12": "arn:aws:lambda:eu-central-1:464622532012:layer:Datadog-Python312:120",
      "python3.12-arm": "arn:aws:lambda:eu-central-1:464622532012:layer:Datadog-Python312-ARM:120",
      "python3.13": "arn:aws:lambda:eu-central-1:464622532012:layer:Datadog-Python313:120",
      "python3.13-arm": "arn:aws:lambda:eu-central-1:464622532012:layer:Datadog-Python313-ARM:120",
      "python3.14": "arn:aws:lambda:eu-central-1:464622532012:layer:Datadog-Python314:120",
      "python3.14-arm": "arn:aws:lambda:eu-central-1:464622532012:layer:Datadog-Python314-ARM:120",
      "ruby3.2": "arn:aws:lambda:eu-central-1:464622532012:layer:Datadog-Ruby3-2:27",
      "ruby3.2-arm": "arn:aws:lambda:eu-central-1:464622532012:layer:Datadog-Ruby3-2-ARM:27",
      "ruby3.3": "arn:aws:lambda:eu-central-1:464622532012:layer:Datadog-Ruby3-3:27",
      "ruby3.3-arm": "arn:aws:lambda:eu-central-1:464622532012:layer:Datadog-Ruby3-3-ARM:27",
      "ruby3.4": "arn:aws:lambda:eu-central-1:464622532012:layer:Datadog-Ruby3-4:27",
      "ruby3.4-arm": "arn:aws:lambda:eu-central-1:464622532012:layer:Datadog-Ruby3-4-ARM:27",
      "extension": "arn:aws:lambda:eu-central-1:464622532012:layer:Datadog-Extension:91",
      "extension-arm": "arn:aws:lambda:eu-central-1:464622532012:layer:Datadog-Extension-ARM:91",
      "extension-fips": "arn:aws:lambda:eu-central-1:464622532012:layer:Datadog-Extension-FIPS:91",
      "extension-arm-fips": "arn:aws:lambda:eu-central-1:464622532012:layer:Datadog-Extension-ARM-FIPS:91",
      "dotnet": "arn:aws:lambda:eu-central-1:464622532012:layer:dd-trace-dotnet:23",
      "dotnet-arm": "arn:aws:lambda:eu-central-1:464622532012:layer:dd-trace-dotnet-ARM:23",
      "java": "arn:aws:lambda:eu-central-1:464622532012:layer:dd-trace-java:25"
    },
    "eu-central-2": {
      "nodejs16.x": "arn:aws:lambda:eu-central-2:464622532012:layer:Datadog-Node16-x:120",
      "nodejs18.x": "arn:aws:lambda:eu-central-2:464622532012:layer:Datadog-Node18-x:132",
      "nodejs20.x": "arn:aws:lambda:eu-central-2:464622532012:layer:Datadog-Node20-x:132",
      "nodejs22.x": "arn:aws:lambda:eu-central-2:464622532012:layer:Datadog-Node22-x:132",
      "nodejs24.x": "arn:aws:lambda:eu-central-2:464622532012:layer:Datadog-Node24-x:132",
      "python3.7": "arn:aws:lambda:eu-central-2:464622532012:layer:Datadog-Python37:85",
      "python3.8": "arn:aws:lambda:eu-central-2:464622532012:layer:Datadog-Python38:120",
      "python3.8-arm": "arn:aws:lambda:eu-central-2:464622532012:layer:Datadog-Python38-ARM:120",
      "python3.9": "arn:aws:lambda:eu-central-2:464622532012:layer:Datadog-Python39:120",
      "python3.9-arm": "arn:aws:lambda:eu-central-2:464622532012:layer:Datadog-Python39-ARM:120",
      "python3.10": "arn:aws:lambda:eu-central-2:464622532012:layer:Datadog-Python310:120",
      "python3.10-arm": "arn:aws:lambda:eu-central-2:464622532012:layer:Datadog-Python310-ARM:120",
      "python3.11": "arn:aws:lambda:eu-central-2:464622532012:layer:Datadog-Python311:120",
      "python3.11-arm": "arn:aws:lambda:eu-central-2:464622532012:layer:Datadog-Python311-ARM:120",
      "python3.12": "arn:aws:lambda:eu-central-2:464622532012:layer:Datadog-Python312:120",
      "python3.12-arm": "arn:aws:lambda:eu-central-2:464622532012:layer:Datadog-Python312-ARM:120",
      "python3.13": "arn:aws:lambda:eu-central-2:464622532012:layer:Datadog-Python313:120",
      "python3.13-arm": "arn:aws:lambda:eu-central-2:464622532012:layer:Datadog-Python313-ARM:120",
      "python3.14": "arn:aws:lambda:eu-central-2:464622532012:layer:Datadog-Python314:120",
      "python3.14-arm": "arn:aws:lambda:eu-central-2:464622532012:layer:Datadog-Python314-ARM:120",
      "ruby3.2": "arn:aws:lambda:eu-central-2:464622532012:layer:Datadog-Ruby3-2:27",
      "ruby3.2-arm": "arn:aws:lambda:eu-central-2:464622532012:layer:Datadog-Ruby3-2-ARM:27",
      "ruby3.3": "arn:aws:lambda:eu-central-2:464622532012:layer:Datadog-Ruby3-3:27",
      "ruby3.3-arm": "arn:aws:lambda:eu-central-2:464622532012:layer:Datadog-Ruby3-3-ARM:27",
      "ruby3.4": "arn:aws:lambda:eu-central-2:464622532012:layer:Datadog-Ruby3-4:27",
      "ruby3.4-arm": "arn:aws:lambda:eu-central-2:464622532012:layer:Datadog-Ruby3-4-ARM:27",
      "extension": "arn:aws:lambda:eu-central-2:464622532012:layer:Datadog-Extension:91",
      "extension-arm": "arn:aws:lambda:eu-central-2:464622532012:layer:Datadog-Extension-ARM:91",
      "extension-fips": "arn:aws:lambda:eu-central-2:464622532012:layer:Datadog-Extension-FIPS:91",
      "extension-arm-fips": "arn:aws:lambda:eu-central-2:464622532012:layer:Datadog-Extension-ARM-FIPS:91",
      "dotnet": "arn:aws:lambda:eu-central-2:464622532012:layer:dd-trace-dotnet:23",
      "dotnet-arm": "arn:aws:lambda:eu-central-2:464622532012:layer:dd-trace-dotnet-ARM:23",
      "java": "arn:aws:lambda:eu-central-2:464622532012:layer:dd-trace-java:25"
    },
    "us-west-1": {
      "nodejs16.x": "arn:aws:lambda:us-west-1:464622532012:layer:Datadog-Node16-x:120",
      "nodejs18.x": "arn:aws:lambda:us-west-1:464622532012:layer:Datadog-Node18-x:132",
      "nodejs20.x": "arn:aws:lambda:us-west-1:464622532012:layer:Datadog-Node20-x:132",
      "nodejs22.x": "arn:aws:lambda:us-west-1:464622532012:layer:Datadog-Node22-x:132",
      "nodejs24.x": "arn:aws:lambda:us-west-1:464622532012:layer:Datadog-Node24-x:132",
      "python3.7": "arn:aws:lambda:us-west-1:464622532012:layer:Datadog-Python37:85",
      "python3.8": "arn:aws:lambda:us-west-1:464622532012:layer:Datadog-Python38:120",
      "python3.8-arm": "arn:aws:lambda:us-west-1:464622532012:layer:Datadog-Python38-ARM:120",
      "python3.9": "arn:aws:lambda:us-west-1:464622532012:layer:Datadog-Python39:120",
      "python3.9-arm": "arn:aws:lambda:us-west-1:464622532012:layer:Datadog-Python39-ARM:120",
      "python3.10": "arn:aws:lambda:us-west-1:464622532012:layer:Datadog-Python310:120",
      "python3.10-arm": "arn:aws:lambda:us-west-1:464622532012:layer:Datadog-Python310-ARM:120",
      "python3.11": "arn:aws:lambda:us-west-1:464622532012:layer:Datadog-Python311:120",
      "python3.11-arm": "arn:aws:lambda:us-west-1:464622532012:layer:Datadog-Python311-ARM:120",
      "python3.12": "arn:aws:lambda:us-west-1:464622532012:layer:Datadog-Python312:120",
      "python3.12-arm": "arn:aws:lambda:us-west-1:464622532012:layer:Datadog-Python312-ARM:120",
      "python3.13": "arn:aws:lambda:us-west-1:464622532012:layer:Datadog-Python313:120",
      "python3.13-arm": "arn:aws:lambda:us-west-1:464622532012:layer:Datadog-Python313-ARM:120",
      "python3.14": "arn:aws:lambda:us-west-1:464622532012:layer:Datadog-Python314:120",
      "python3.14-arm": "arn:aws:lambda:us-west-1:464622532012:layer:Datadog-Python314-ARM:120",
      "ruby3.2": "arn:aws:lambda:us-west-1:464622532012:layer:Datadog-Ruby3-2:27",
      "ruby3.2-arm": "arn:aws:lambda:us-west-1:464622532012:layer:Datadog-Ruby3-2-ARM:27",
      "ruby3.3": "arn:aws:lambda:us-west-1:464622532012:layer:Datadog-Ruby3-3:27",
      "ruby3.3-arm": "arn:aws:lambda:us-west-1:464622532012:layer:Datadog-Ruby3-3-ARM:27",
      "ruby3.4": "arn:aws:lambda:us-west-1:464622532012:layer:Datadog-Ruby3-4:27",
      "ruby3.4-arm": "arn:aws:lambda:us-west-1:464622532012:layer:Datadog-Ruby3-4-ARM:27",
      "extension": "arn:aws:lambda:us-west-1:464622532012:layer:Datadog-Extension:91",
      "extension-arm": "arn:aws:lambda:us-west-1:464622532012:layer:Datadog-Extension-ARM:91",
      "extension-fips": "arn:aws:lambda:us-west-1:464622532012:layer:Datadog-Extension-FIPS:91",
      "extension-arm-fips": "arn:aws:lambda:us-west-1:464622532012:layer:Datadog-Extension-ARM-FIPS:91",
      "dotnet": "arn:aws:lambda:us-west-1:464622532012:layer:dd-trace-dotnet:23",
      "dotnet-arm": "arn:aws:lambda:us-west-1:464622532012:layer:dd-trace-dotnet-ARM:23",
      "java": "arn:aws:lambda:us-west-1:464622532012:layer:dd-trace-java:25"
    },
    "us-west-2": {
      "nodejs16.x": "arn:aws:lambda:us-west-2:464622532012:layer:Datadog-Node16-x:120",
      "nodejs18.x": "arn:aws:lambda:us-west-2:464622532012:layer:Datadog-Node18-x:132",
      "nodejs20.x": "arn:aws:lambda:us-west-2:464622532012:layer:Datadog-Node20-x:132",
      "nodejs22.x": "arn:aws:lambda:us-west-2:464622532012:layer:Datadog-Node22-x:132",
      "nodejs24.x": "arn:aws:lambda:us-west-2:464622532012:layer:Datadog-Node24-x:132",
      "python3.7": "arn:aws:lambda:us-west-2:464622532012:layer:Datadog-Python37:85",
      "python3.8": "arn:aws:lambda:us-west-2:464622532012:layer:Datadog-Python38:120",
      "python3.8-arm": "arn:aws:lambda:us-west-2:464622532012:layer:Datadog-Python38-ARM:120",
      "python3.9": "arn:aws:lambda:us-west-2:464622532012:layer:Datadog-Python39:120",
      "python3.9-arm": "arn:aws:lambda:us-west-2:464622532012:layer:Datadog-Python39-ARM:120",
      "python3.10": "arn:aws:lambda:us-west-2:464622532012:layer:Datadog-Python310:120",
      "python3.10-arm": "arn:aws:lambda:us-west-2:464622532012:layer:Datadog-Python310-ARM:120",
      "python3.11": "arn:aws:lambda:us-west-2:464622532012:layer:Datadog-Python311:120",
      "python3.11-arm": "arn:aws:lambda:us-west-2:464622532012:layer:Datadog-Python311-ARM:120",
      "python3.12": "arn:aws:lambda:us-west-2:464622532012:layer:Datadog-Python312:120",
      "python3.12-arm": "arn:aws:lambda:us-west-2:464622532012:layer:Datadog-Python312-ARM:120",
      "python3.13": "arn:aws:lambda:us-west-2:464622532012:layer:Datadog-Python313:120",
      "python3.13-arm": "arn:aws:lambda:us-west-2:464622532012:layer:Datadog-Python313-ARM:120",
      "python3.14": "arn:aws:lambda:us-west-2:464622532012:layer:Datadog-Python314:120",
      "python3.14-arm": "arn:aws:lambda:us-west-2:464622532012:layer:Datadog-Python314-ARM:120",
      "ruby3.2": "arn:aws:lambda:us-west-2:464622532012:layer:Datadog-Ruby3-2:27",
      "ruby3.2-arm": "arn:aws:lambda:us-west-2:464622532012:layer:Datadog-Ruby3-2-ARM:27",
      "ruby3.3": "arn:aws:lambda:us-west-2:464622532012:layer:Datadog-Ruby3-3:27",
      "ruby3.3-arm": "arn:aws:lambda:us-west-2:464622532012:layer:Datadog-Ruby3-3-ARM:27",
      "ruby3.4": "arn:aws:lambda:us-west-2:464622532012:layer:Datadog-Ruby3-4:27",
      "ruby3.4-arm": "arn:aws:lambda:us-west-2:464622532012:layer:Datadog-Ruby3-4-ARM:27",
      "extension": "arn:aws:lambda:us-west-2:464622532012:layer:Datadog-Extension:91",
      "extension-arm": "arn:aws:lambda:us-west-2:464622532012:layer:Datadog-Extension-ARM:91",
      "extension-fips": "arn:aws:lambda:us-west-2:464622532012:layer:Datadog-Extension-FIPS:91",
      "extension-arm-fips": "arn:aws:lambda:us-west-2:464622532012:layer:Datadog-Extension-ARM-FIPS:91",
      "dotnet": "arn:aws:lambda:us-west-2:464622532012:layer:dd-trace-dotnet:23",
      "dotnet-arm": "arn:aws:lambda:us-west-2:464622532012:layer:dd-trace-dotnet-ARM:23",
      "java": "arn:aws:lambda:us-west-2:464622532012:layer:dd-trace-java:25"
    },
    "af-south-1": {
      "nodejs16.x": "arn:aws:lambda:af-south-1:464622532012:layer:Datadog-Node16-x:120",
      "nodejs18.x": "arn:aws:lambda:af-south-1:464622532012:layer:Datadog-Node18-x:132",
      "nodejs20.x": "arn:aws:lambda:af-south-1:464622532012:layer:Datadog-Node20-x:132",
      "nodejs22.x": "arn:aws:lambda:af-south-1:464622532012:layer:Datadog-Node22-x:132",
      "nodejs24.x": "arn:aws:lambda:af-south-1:464622532012:layer:Datadog-Node24-x:132",
      "python3.7": "arn:aws:lambda:af-south-1:464622532012:layer:Datadog-Python37:85",
      "python3.8": "arn:aws:lambda:af-south-1:464622532012:layer:Datadog-Python38:120",
      "python3.8-arm": "arn:aws:lambda:af-south-1:464622532012:layer:Datadog-Python38-ARM:120",
      "python3.9": "arn:aws:lambda:af-south-1:464622532012:layer:Datadog-Python39:120",
      "python3.9-arm": "arn:aws:lambda:af-south-1:464622532012:layer:Datadog-Python39-ARM:120",
      "python3.10": "arn:aws:lambda:af-south-1:464622532012:layer:Datadog-Python310:120",
      "python3.10-arm": "arn:aws:lambda:af-south-1:464622532012:layer:Datadog-Python310-ARM:120",
      "python3.11": "arn:aws:lambda:af-south-1:464622532012:layer:Datadog-Python311:120",
      "python3.11-arm": "arn:aws:lambda:af-south-1:464622532012:layer:Datadog-Python311-ARM:120",
      "python3.12": "arn:aws:lambda:af-south-1:464622532012:layer:Datadog-Python312:120",
      "python3.12-arm": "arn:aws:lambda:af-south-1:464622532012:layer:Datadog-Python312-ARM:120",
      "python3.13": "arn:aws:lambda:af-south-1:464622532012:layer:Datadog-Python313:120",
      "python3.13-arm": "arn:aws:lambda:af-south-1:464622532012:layer:Datadog-Python313-ARM:120",
      "python3.14": "arn:aws:lambda:af-south-1:464622532012:layer:Datadog-Python314:120",
      "python3.14-arm": "arn:aws:lambda:af-south-1:464622532012:layer:Datadog-Python314-ARM:120",
      "ruby3.2": "arn:aws:lambda:af-south-1:464622532012:layer:Datadog-Ruby3-2:27",
      "ruby3.2-arm": "arn:aws:lambda:af-south-1:464622532012:layer:Datadog-Ruby3-2-ARM:27",
      "ruby3.3": "arn:aws:lambda:af-south-1:464622532012:layer:Datadog-Ruby3-3:27",
      "ruby3.3-arm": "arn:aws:lambda:af-south-1:464622532012:layer:Datadog-Ruby3-3-ARM:27",
      "ruby3.4": "arn:aws:lambda:af-south-1:464622532012:layer:Datadog-Ruby3-4:27",
      "ruby3.4-arm": "arn:aws:lambda:af-south-1:464622532012:layer:Datadog-Ruby3-4-ARM:27",
      "extension": "arn:aws:lambda:af-south-1:464622532012:layer:Datadog-Extension:91",
      "extension-arm": "arn:aws:lambda:af-south-1:464622532012:layer:Datadog-Extension-ARM:91",
      "extension-fips": "arn:aws:lambda:af-south-1:464622532012:layer:Datadog-Extension-FIPS:91",
      "extension-arm-fips": "arn:aws:lambda:af-south-1:464622532012:layer:Datadog-Extension-ARM-FIPS:91",
      "dotnet": "arn:aws:lambda:af-south-1:464622532012:layer:dd-trace-dotnet:23",
      "dotnet-arm": "arn:aws:lambda:af-south-1:464622532012:layer:dd-trace-dotnet-ARM:23",
      "java": "arn:aws:lambda:af-south-1:464622532012:layer:dd-trace-java:25"
    },
    "eu-north-1": {
      "nodejs16.x": "arn:aws:lambda:eu-north-1:464622532012:layer:Datadog-Node16-x:120",
      "nodejs18.x": "arn:aws:lambda:eu-north-1:464622532012:layer:Datadog-Node18-x:132",
      "nodejs20.x": "arn:aws:lambda:eu-north-1:464622532012:layer:Datadog-Node20-x:132",
      "nodejs22.x": "arn:aws:lambda:eu-north-1:464622532012:layer:Datadog-Node22-x:132",
      "nodejs24.x": "arn:aws:lambda:eu-north-1:464622532012:layer:Datadog-Node24-x:132",
      "python3.7": "arn:aws:lambda:eu-north-1:464622532012:layer:Datadog-Python37:85",
      "python3.8": "arn:aws:lambda:eu-north-1:464622532012:layer:Datadog-Python38:120",
      "python3.8-arm": "arn:aws:lambda:eu-north-1:464622532012:layer:Datadog-Python38-ARM:120",
      "python3.9": "arn:aws:lambda:eu-north-1:464622532012:layer:Datadog-Python39:120",
      "python3.9-arm": "arn:aws:lambda:eu-north-1:464622532012:layer:Datadog-Python39-ARM:120",
      "python3.10": "arn:aws:lambda:eu-north-1:464622532012:layer:Datadog-Python310:120",
      "python3.10-arm": "arn:aws:lambda:eu-north-1:464622532012:layer:Datadog-Python310-ARM:120",
      "python3.11": "arn:aws:lambda:eu-north-1:464622532012:layer:Datadog-Python311:120",
      "python3.11-arm": "arn:aws:lambda:eu-north-1:464622532012:layer:Datadog-Python311-ARM:120",
      "python3.12": "arn:aws:lambda:eu-north-1:464622532012:layer:Datadog-Python312:120",
      "python3.12-arm": "arn:aws:lambda:eu-north-1:464622532012:layer:Datadog-Python312-ARM:120",
      "python3.13": "arn:aws:lambda:eu-north-1:464622532012:layer:Datadog-Python313:120",
      "python3.13-arm": "arn:aws:lambda:eu-north-1:464622532012:layer:Datadog-Python313-ARM:120",
      "python3.14": "arn:aws:lambda:eu-north-1:464622532012:layer:Datadog-Python314:120",
      "python3.14-arm": "arn:aws:lambda:eu-north-1:464622532012:layer:Datadog-Python314-ARM:120",
      "ruby3.2": "arn:aws:lambda:eu-north-1:464622532012:layer:Datadog-Ruby3-2:27",
      "ruby3.2-arm": "arn:aws:lambda:eu-north-1:464622532012:layer:Datadog-Ruby3-2-ARM:27",
      "ruby3.3": "arn:aws:lambda:eu-north-1:464622532012:layer:Datadog-Ruby3-3:27",
      "ruby3.3-arm": "arn:aws:lambda:eu-north-1:464622532012:layer:Datadog-Ruby3-3-ARM:27",
      "ruby3.4": "arn:aws:lambda:eu-north-1:464622532012:layer:Datadog-Ruby3-4:27",
      "ruby3.4-arm": "arn:aws:lambda:eu-north-1:464622532012:layer:Datadog-Ruby3-4-ARM:27",
      "extension": "arn:aws:lambda:eu-north-1:464622532012:layer:Datadog-Extension:91",
      "extension-arm": "arn:aws:lambda:eu-north-1:464622532012:layer:Datadog-Extension-ARM:91",
      "extension-fips": "arn:aws:lambda:eu-north-1:464622532012:layer:Datadog-Extension-FIPS:91",
      "extension-arm-fips": "arn:aws:lambda:eu-north-1:464622532012:layer:Datadog-Extension-ARM-FIPS:91",
      "dotnet": "arn:aws:lambda:eu-north-1:464622532012:layer:dd-trace-dotnet:23",
      "dotnet-arm": "arn:aws:lambda:eu-north-1:464622532012:layer:dd-trace-dotnet-ARM:23",
      "java": "arn:aws:lambda:eu-north-1:464622532012:layer:dd-trace-java:25"
    },
    "eu-west-3": {
      "nodejs16.x": "arn:aws:lambda:eu-west-3:464622532012:layer:Datadog-Node16-x:120",
      "nodejs18.x": "arn:aws:lambda:eu-west-3:464622532012:layer:Datadog-Node18-x:132",
      "nodejs20.x": "arn:aws:lambda:eu-west-3:464622532012:layer:Datadog-Node20-x:132",
      "nodejs22.x": "arn:aws:lambda:eu-west-3:464622532012:layer:Datadog-Node22-x:132",
      "nodejs24.x": "arn:aws:lambda:eu-west-3:464622532012:layer:Datadog-Node24-x:132",
      "python3.7": "arn:aws:lambda:eu-west-3:464622532012:layer:Datadog-Python37:85",
      "python3.8": "arn:aws:lambda:eu-west-3:464622532012:layer:Datadog-Python38:120",
      "python3.8-arm": "arn:aws:lambda:eu-west-3:464622532012:layer:Datadog-Python38-ARM:120",
      "python3.9": "arn:aws:lambda:eu-west-3:464622532012:layer:Datadog-Python39:120",
      "python3.9-arm": "arn:aws:lambda:eu-west-3:464622532012:layer:Datadog-Python39-ARM:120",
      "python3.10": "arn:aws:lambda:eu-west-3:464622532012:layer:Datadog-Python310:120",
      "python3.10-arm": "arn:aws:lambda:eu-west-3:464622532012:layer:Datadog-Python310-ARM:120",
      "python3.11": "arn:aws:lambda:eu-west-3:464622532012:layer:Datadog-Python311:120",
      "python3.11-arm": "arn:aws:lambda:eu-west-3:464622532012:layer:Datadog-Python311-ARM:120",
      "python3.12": "arn:aws:lambda:eu-west-3:464622532012:layer:Datadog-Python312:120",
      "python3.12-arm": "arn:aws:lambda:eu-west-3:464622532012:layer:Datadog-Python312-ARM:120",
      "python3.13": "arn:aws:lambda:eu-west-3:464622532012:layer:Datadog-Python313:120",
      "python3.13-arm": "arn:aws:lambda:eu-west-3:464622532012:layer:Datadog-Python313-ARM:120",
      "python3.14": "arn:aws:lambda:eu-west-3:464622532012:layer:Datadog-Python314:120",
      "python3.14-arm": "arn:aws:lambda:eu-west-3:464622532012:layer:Datadog-Python314-ARM:120",
      "ruby3.2": "arn:aws:lambda:eu-west-3:464622532012:layer:Datadog-Ruby3-2:27",
      "ruby3.2-arm": "arn:aws:lambda:eu-west-3:464622532012:layer:Datadog-Ruby3-2-ARM:27",
      "ruby3.3": "arn:aws:lambda:eu-west-3:464622532012:layer:Datadog-Ruby3-3:27",
      "ruby3.3-arm": "arn:aws:lambda:eu-west-3:464622532012:layer:Datadog-Ruby3-3-ARM:27",
      "ruby3.4": "arn:aws:lambda:eu-west-3:464622532012:layer:Datadog-Ruby3-4:27",
      "ruby3.4-arm": "arn:aws:lambda:eu-west-3:464622532012:layer:Datadog-Ruby3-4-ARM:27",
      "extension": "arn:aws:lambda:eu-west-3:464622532012:layer:Datadog-Extension:91",
      "extension-arm": "arn:aws:lambda:eu-west-3:464622532012:layer:Datadog-Extension-ARM:91",
      "extension-fips": "arn:aws:lambda:eu-west-3:464622532012:layer:Datadog-Extension-FIPS:91",
      "extension-arm-fips": "arn:aws:lambda:eu-west-3:464622532012:layer:Datadog-Extension-ARM-FIPS:91",
      "dotnet": "arn:aws:lambda:eu-west-3:464622532012:layer:dd-trace-dotnet:23",
      "dotnet-arm": "arn:aws:lambda:eu-west-3:464622532012:layer:dd-trace-dotnet-ARM:23",
      "java": "arn:aws:lambda:eu-west-3:464622532012:layer:dd-trace-java:25"
    },
    "eu-west-2": {
      "nodejs16.x": "arn:aws:lambda:eu-west-2:464622532012:layer:Datadog-Node16-x:120",
      "nodejs18.x": "arn:aws:lambda:eu-west-2:464622532012:layer:Datadog-Node18-x:132",
      "nodejs20.x": "arn:aws:lambda:eu-west-2:464622532012:layer:Datadog-Node20-x:132",
      "nodejs22.x": "arn:aws:lambda:eu-west-2:464622532012:layer:Datadog-Node22-x:132",
      "nodejs24.x": "arn:aws:lambda:eu-west-2:464622532012:layer:Datadog-Node24-x:132",
      "python3.7": "arn:aws:lambda:eu-west-2:464622532012:layer:Datadog-Python37:85",
      "python3.8": "arn:aws:lambda:eu-west-2:464622532012:layer:Datadog-Python38:120",
      "python3.8-arm": "arn:aws:lambda:eu-west-2:464622532012:layer:Datadog-Python38-ARM:120",
      "python3.9": "arn:aws:lambda:eu-west-2:464622532012:layer:Datadog-Python39:120",
      "python3.9-arm": "arn:aws:lambda:eu-west-2:464622532012:layer:Datadog-Python39-ARM:120",
      "python3.10": "arn:aws:lambda:eu-west-2:464622532012:layer:Datadog-Python310:120",
      "python3.10-arm": "arn:aws:lambda:eu-west-2:464622532012:layer:Datadog-Python310-ARM:120",
      "python3.11": "arn:aws:lambda:eu-west-2:464622532012:layer:Datadog-Python311:120",
      "python3.11-arm": "arn:aws:lambda:eu-west-2:464622532012:layer:Datadog-Python311-ARM:120",
      "python3.12": "arn:aws:lambda:eu-west-2:464622532012:layer:Datadog-Python312:120",
      "python3.12-arm": "arn:aws:lambda:eu-west-2:464622532012:layer:Datadog-Python312-ARM:120",
      "python3.13": "arn:aws:lambda:eu-west-2:464622532012:layer:Datadog-Python313:120",
      "python3.13-arm": "arn:aws:lambda:eu-west-2:464622532012:layer:Datadog-Python313-ARM:120",
      "python3.14": "arn:aws:lambda:eu-west-2:464622532012:layer:Datadog-Python314:120",
      "python3.14-arm": "arn:aws:lambda:eu-west-2:464622532012:layer:Datadog-Python314-ARM:120",
      "ruby3.2": "arn:aws:lambda:eu-west-2:464622532012:layer:Datadog-Ruby3-2:27",
      "ruby3.2-arm": "arn:aws:lambda:eu-west-2:464622532012:layer:Datadog-Ruby3-2-ARM:27",
      "ruby3.3": "arn:aws:lambda:eu-west-2:464622532012:layer:Datadog-Ruby3-3:27",
      "ruby3.3-arm": "arn:aws:lambda:eu-west-2:464622532012:layer:Datadog-Ruby3-3-ARM:27",
      "ruby3.4": "arn:aws:lambda:eu-west-2:464622532012:layer:Datadog-Ruby3-4:27",
      "ruby3.4-arm": "arn:aws:lambda:eu-west-2:464622532012:layer:Datadog-Ruby3-4-ARM:27",
      "extension": "arn:aws:lambda:eu-west-2:464622532012:layer:Datadog-Extension:91",
      "extension-arm": "arn:aws:lambda:eu-west-2:464622532012:layer:Datadog-Extension-ARM:91",
      "extension-fips": "arn:aws:lambda:eu-west-2:464622532012:layer:Datadog-Extension-FIPS:91",
      "extension-arm-fips": "arn:aws:lambda:eu-west-2:464622532012:layer:Datadog-Extension-ARM-FIPS:91",
      "dotnet": "arn:aws:lambda:eu-west-2:464622532012:layer:dd-trace-dotnet:23",
      "dotnet-arm": "arn:aws:lambda:eu-west-2:464622532012:layer:dd-trace-dotnet-ARM:23",
      "java": "arn:aws:lambda:eu-west-2:464622532012:layer:dd-trace-java:25"
    },
    "eu-west-1": {
      "nodejs16.x": "arn:aws:lambda:eu-west-1:464622532012:layer:Datadog-Node16-x:120",
      "nodejs18.x": "arn:aws:lambda:eu-west-1:464622532012:layer:Datadog-Node18-x:132",
      "nodejs20.x": "arn:aws:lambda:eu-west-1:464622532012:layer:Datadog-Node20-x:132",
      "nodejs22.x": "arn:aws:lambda:eu-west-1:464622532012:layer:Datadog-Node22-x:132",
      "nodejs24.x": "arn:aws:lambda:eu-west-1:464622532012:layer:Datadog-Node24-x:132",
      "python3.7": "arn:aws:lambda:eu-west-1:464622532012:layer:Datadog-Python37:85",
      "python3.8": "arn:aws:lambda:eu-west-1:464622532012:layer:Datadog-Python38:120",
      "python3.8-arm": "arn:aws:lambda:eu-west-1:464622532012:layer:Datadog-Python38-ARM:120",
      "python3.9": "arn:aws:lambda:eu-west-1:464622532012:layer:Datadog-Python39:120",
      "python3.9-arm": "arn:aws:lambda:eu-west-1:464622532012:layer:Datadog-Python39-ARM:120",
      "python3.10": "arn:aws:lambda:eu-west-1:464622532012:layer:Datadog-Python310:120",
      "python3.10-arm": "arn:aws:lambda:eu-west-1:464622532012:layer:Datadog-Python310-ARM:120",
      "python3.11": "arn:aws:lambda:eu-west-1:464622532012:layer:Datadog-Python311:120",
      "python3.11-arm": "arn:aws:lambda:eu-west-1:464622532012:layer:Datadog-Python311-ARM:120",
      "python3.12": "arn:aws:lambda:eu-west-1:464622532012:layer:Datadog-Python312:120",
      "python3.12-arm": "arn:aws:lambda:eu-west-1:464622532012:layer:Datadog-Python312-ARM:120",
      "python3.13": "arn:aws:lambda:eu-west-1:464622532012:layer:Datadog-Python313:120",
      "python3.13-arm": "arn:aws:lambda:eu-west-1:464622532012:layer:Datadog-Python313-ARM:120",
      "python3.14": "arn:aws:lambda:eu-west-1:464622532012:layer:Datadog-Python314:120",
      "python3.14-arm": "arn:aws:lambda:eu-west-1:464622532012:layer:Datadog-Python314-ARM:120",
      "ruby3.2": "arn:aws:lambda:eu-west-1:464622532012:layer:Datadog-Ruby3-2:27",
      "ruby3.2-arm": "arn:aws:lambda:eu-west-1:464622532012:layer:Datadog-Ruby3-2-ARM:27",
      "ruby3.3": "arn:aws:lambda:eu-west-1:464622532012:layer:Datadog-Ruby3-3:27",
      "ruby3.3-arm": "arn:aws:lambda:eu-west-1:464622532012:layer:Datadog-Ruby3-3-ARM:27",
      "ruby3.4": "arn:aws:lambda:eu-west-1:464622532012:layer:Datadog-Ruby3-4:27",
      "ruby3.4-arm": "arn:aws:lambda:eu-west-1:464622532012:layer:Datadog-Ruby3-4-ARM:27",
      "extension": "arn:aws:lambda:eu-west-1:464622532012:layer:Datadog-Extension:91",
      "extension-arm": "arn:aws:lambda:eu-west-1:464622532012:layer:Datadog-Extension-ARM:91",
      "extension-fips": "arn:aws:lambda:eu-west-1:464622532012:layer:Datadog-Extension-FIPS:91",
      "extension-arm-fips": "arn:aws:lambda:eu-west-1:464622532012:layer:Datadog-Extension-ARM-FIPS:91",
      "dotnet": "arn:aws:lambda:eu-west-1:464622532012:layer:dd-trace-dotnet:23",
      "dotnet-arm": "arn:aws:lambda:eu-west-1:464622532012:layer:dd-trace-dotnet-ARM:23",
      "java": "arn:aws:lambda:eu-west-1:464622532012:layer:dd-trace-java:25"
    },
    "ap-northeast-3": {
      "nodejs16.x": "arn:aws:lambda:ap-northeast-3:464622532012:layer:Datadog-Node16-x:120",
      "nodejs18.x": "arn:aws:lambda:ap-northeast-3:464622532012:layer:Datadog-Node18-x:132",
      "nodejs20.x": "arn:aws:lambda:ap-northeast-3:464622532012:layer:Datadog-Node20-x:132",
      "nodejs22.x": "arn:aws:lambda:ap-northeast-3:464622532012:layer:Datadog-Node22-x:132",
      "nodejs24.x": "arn:aws:lambda:ap-northeast-3:464622532012:layer:Datadog-Node24-x:132",
      "python3.7": "arn:aws:lambda:ap-northeast-3:464622532012:layer:Datadog-Python37:85",
      "python3.8": "arn:aws:lambda:ap-northeast-3:464622532012:layer:Datadog-Python38:120",
      "python3.8-arm": "arn:aws:lambda:ap-northeast-3:464622532012:layer:Datadog-Python38-ARM:120",
      "python3.9": "arn:aws:lambda:ap-northeast-3:464622532012:layer:Datadog-Python39:120",
      "python3.9-arm": "arn:aws:lambda:ap-northeast-3:464622532012:layer:Datadog-Python39-ARM:120",
      "python3.10": "arn:aws:lambda:ap-northeast-3:464622532012:layer:Datadog-Python310:120",
      "python3.10-arm": "arn:aws:lambda:ap-northeast-3:464622532012:layer:Datadog-Python310-ARM:120",
      "python3.11": "arn:aws:lambda:ap-northeast-3:464622532012:layer:Datadog-Python311:120",
      "python3.11-arm": "arn:aws:lambda:ap-northeast-3:464622532012:layer:Datadog-Python311-ARM:120",
      "python3.12": "arn:aws:lambda:ap-northeast-3:464622532012:layer:Datadog-Python312:120",
      "python3.12-arm": "arn:aws:lambda:ap-northeast-3:464622532012:layer:Datadog-Python312-ARM:120",
      "python3.13": "arn:aws:lambda:ap-northeast-3:464622532012:layer:Datadog-Python313:120",
      "python3.13-arm": "arn:aws:lambda:ap-northeast-3:464622532012:layer:Datadog-Python313-ARM:120",
      "python3.14": "arn:aws:lambda:ap-northeast-3:464622532012:layer:Datadog-Python314:120",
      "python3.14-arm": "arn:aws:lambda:ap-northeast-3:464622532012:layer:Datadog-Python314-ARM:120",
      "ruby3.2": "arn:aws:lambda:ap-northeast-3:464622532012:layer:Datadog-Ruby3-2:27",
      "ruby3.2-arm": "arn:aws:lambda:ap-northeast-3:464622532012:layer:Datadog-Ruby3-2-ARM:27",
      "ruby3.3": "arn:aws:lambda:ap-northeast-3:464622532012:layer:Datadog-Ruby3-3:27",
      "ruby3.3-arm": "arn:aws:lambda:ap-northeast-3:464622532012:layer:Datadog-Ruby3-3-ARM:27",
      "ruby3.4": "arn:aws:lambda:ap-northeast-3:464622532012:layer:Datadog-Ruby3-4:27",
      "ruby3.4-arm": "arn:aws:lambda:ap-northeast-3:464622532012:layer:Datadog-Ruby3-4-ARM:27",
      "extension": "arn:aws:lambda:ap-northeast-3:464622532012:layer:Datadog-Extension:91",
      "extension-arm": "arn:aws:lambda:ap-northeast-3:464622532012:layer:Datadog-Extension-ARM:91",
      "extension-fips": "arn:aws:lambda:ap-northeast-3:464622532012:layer:Datadog-Extension-FIPS:91",
      "extension-arm-fips": "arn:aws:lambda:ap-northeast-3:464622532012:layer:Datadog-Extension-ARM-FIPS:91",
      "dotnet": "arn:aws:lambda:ap-northeast-3:464622532012:layer:dd-trace-dotnet:23",
      "dotnet-arm": "arn:aws:lambda:ap-northeast-3:464622532012:layer:dd-trace-dotnet-ARM:23",
      "java": "arn:aws:lambda:ap-northeast-3:464622532012:layer:dd-trace-java:25"
    },
    "ap-northeast-2": {
      "nodejs16.x": "arn:aws:lambda:ap-northeast-2:464622532012:layer:Datadog-Node16-x:120",
      "nodejs18.x": "arn:aws:lambda:ap-northeast-2:464622532012:layer:Datadog-Node18-x:132",
      "nodejs20.x": "arn:aws:lambda:ap-northeast-2:464622532012:layer:Datadog-Node20-x:132",
      "nodejs22.x": "arn:aws:lambda:ap-northeast-2:464622532012:layer:Datadog-Node22-x:132",
      "nodejs24.x": "arn:aws:lambda:ap-northeast-2:464622532012:layer:Datadog-Node24-x:132",
      "python3.7": "arn:aws:lambda:ap-northeast-2:464622532012:layer:Datadog-Python37:85",
      "python3.8": "arn:aws:lambda:ap-northeast-2:464622532012:layer:Datadog-Python38:120",
      "python3.8-arm": "arn:aws:lambda:ap-northeast-2:464622532012:layer:Datadog-Python38-ARM:120",
      "python3.9": "arn:aws:lambda:ap-northeast-2:464622532012:layer:Datadog-Python39:120",
      "python3.9-arm": "arn:aws:lambda:ap-northeast-2:464622532012:layer:Datadog-Python39-ARM:120",
      "python3.10": "arn:aws:lambda:ap-northeast-2:464622532012:layer:Datadog-Python310:120",
      "python3.10-arm": "arn:aws:lambda:ap-northeast-2:464622532012:layer:Datadog-Python310-ARM:120",
      "python3.11": "arn:aws:lambda:ap-northeast-2:464622532012:layer:Datadog-Python311:120",
      "python3.11-arm": "arn:aws:lambda:ap-northeast-2:464622532012:layer:Datadog-Python311-ARM:120",
      "python3.12": "arn:aws:lambda:ap-northeast-2:464622532012:layer:Datadog-Python312:120",
      "python3.12-arm": "arn:aws:lambda:ap-northeast-2:464622532012:layer:Datadog-Python312-ARM:120",
      "python3.13": "arn:aws:lambda:ap-northeast-2:464622532012:layer:Datadog-Python313:120",
      "python3.13-arm": "arn:aws:lambda:ap-northeast-2:464622532012:layer:Datadog-Python313-ARM:120",
      "python3.14": "arn:aws:lambda:ap-northeast-2:464622532012:layer:Datadog-Python314:120",
      "python3.14-arm": "arn:aws:lambda:ap-northeast-2:464622532012:layer:Datadog-Python314-ARM:120",
      "ruby3.2": "arn:aws:lambda:ap-northeast-2:464622532012:layer:Datadog-Ruby3-2:27",
      "ruby3.2-arm": "arn:aws:lambda:ap-northeast-2:464622532012:layer:Datadog-Ruby3-2-ARM:27",
      "ruby3.3": "arn:aws:lambda:ap-northeast-2:464622532012:layer:Datadog-Ruby3-3:27",
      "ruby3.3-arm": "arn:aws:lambda:ap-northeast-2:464622532012:layer:Datadog-Ruby3-3-ARM:27",
      "ruby3.4": "arn:aws:lambda:ap-northeast-2:464622532012:layer:Datadog-Ruby3-4:27",
      "ruby3.4-arm": "arn:aws:lambda:ap-northeast-2:464622532012:layer:Datadog-Ruby3-4-ARM:27",
      "extension": "arn:aws:lambda:ap-northeast-2:464622532012:layer:Datadog-Extension:91",
      "extension-arm": "arn:aws:lambda:ap-northeast-2:464622532012:layer:Datadog-Extension-ARM:91",
      "extension-fips": "arn:aws:lambda:ap-northeast-2:464622532012:layer:Datadog-Extension-FIPS:91",
      "extension-arm-fips": "arn:aws:lambda:ap-northeast-2:464622532012:layer:Datadog-Extension-ARM-FIPS:91",
      "dotnet": "arn:aws:lambda:ap-northeast-2:464622532012:layer:dd-trace-dotnet:23",
      "dotnet-arm": "arn:aws:lambda:ap-northeast-2:464622532012:layer:dd-trace-dotnet-ARM:23",
      "java": "arn:aws:lambda:ap-northeast-2:464622532012:layer:dd-trace-java:25"
    },
    "me-south-1": {
      "nodejs16.x": "arn:aws:lambda:me-south-1:464622532012:layer:Datadog-Node16-x:120",
      "nodejs18.x": "arn:aws:lambda:me-south-1:464622532012:layer:Datadog-Node18-x:132",
      "nodejs20.x": "arn:aws:lambda:me-south-1:464622532012:layer:Datadog-Node20-x:132",
      "nodejs22.x": "arn:aws:lambda:me-south-1:464622532012:layer:Datadog-Node22-x:132",
      "nodejs24.x": "arn:aws:lambda:me-south-1:464622532012:layer:Datadog-Node24-x:132",
      "python3.7": "arn:aws:lambda:me-south-1:464622532012:layer:Datadog-Python37:85",
      "python3.8": "arn:aws:lambda:me-south-1:464622532012:layer:Datadog-Python38:120",
      "python3.8-arm": "arn:aws:lambda:me-south-1:464622532012:layer:Datadog-Python38-ARM:120",
      "python3.9": "arn:aws:lambda:me-south-1:464622532012:layer:Datadog-Python39:120",
      "python3.9-arm": "arn:aws:lambda:me-south-1:464622532012:layer:Datadog-Python39-ARM:120",
      "python3.10": "arn:aws:lambda:me-south-1:464622532012:layer:Datadog-Python310:120",
      "python3.10-arm": "arn:aws:lambda:me-south-1:464622532012:layer:Datadog-Python310-ARM:120",
      "python3.11": "arn:aws:lambda:me-south-1:464622532012:layer:Datadog-Python311:120",
      "python3.11-arm": "arn:aws:lambda:me-south-1:464622532012:layer:Datadog-Python311-ARM:120",
      "python3.12": "arn:aws:lambda:me-south-1:464622532012:layer:Datadog-Python312:120",
      "python3.12-arm": "arn:aws:lambda:me-south-1:464622532012:layer:Datadog-Python312-ARM:120",
      "python3.13": "arn:aws:lambda:me-south-1:464622532012:layer:Datadog-Python313:120",
      "python3.13-arm": "arn:aws:lambda:me-south-1:464622532012:layer:Datadog-Python313-ARM:120",
      "python3.14": "arn:aws:lambda:me-south-1:464622532012:layer:Datadog-Python314:120",
      "python3.14-arm": "arn:aws:lambda:me-south-1:464622532012:layer:Datadog-Python314-ARM:120",
      "ruby3.2": "arn:aws:lambda:me-south-1:464622532012:layer:Datadog-Ruby3-2:27",
      "ruby3.2-arm": "arn:aws:lambda:me-south-1:464622532012:layer:Datadog-Ruby3-2-ARM:27",
      "ruby3.3": "arn:aws:lambda:me-south-1:464622532012:layer:Datadog-Ruby3-3:27",
      "ruby3.3-arm": "arn:aws:lambda:me-south-1:464622532012:layer:Datadog-Ruby3-3-ARM:27",
      "ruby3.4": "arn:aws:lambda:me-south-1:464622532012:layer:Datadog-Ruby3-4:27",
      "ruby3.4-arm": "arn:aws:lambda:me-south-1:464622532012:layer:Datadog-Ruby3-4-ARM:27",
      "extension": "arn:aws:lambda:me-south-1:464622532012:layer:Datadog-Extension:91",
      "extension-arm": "arn:aws:lambda:me-south-1:464622532012:layer:Datadog-Extension-ARM:91",
      "extension-fips": "arn:aws:lambda:me-south-1:464622532012:layer:Datadog-Extension-FIPS:91",
      "extension-arm-fips": "arn:aws:lambda:me-south-1:464622532012:layer:Datadog-Extension-ARM-FIPS:91",
      "dotnet": "arn:aws:lambda:me-south-1:464622532012:layer:dd-trace-dotnet:23",
      "dotnet-arm": "arn:aws:lambda:me-south-1:464622532012:layer:dd-trace-dotnet-ARM:23",
      "java": "arn:aws:lambda:me-south-1:464622532012:layer:dd-trace-java:25"
    },
    "ap-northeast-1": {
      "nodejs16.x": "arn:aws:lambda:ap-northeast-1:464622532012:layer:Datadog-Node16-x:120",
      "nodejs18.x": "arn:aws:lambda:ap-northeast-1:464622532012:layer:Datadog-Node18-x:132",
      "nodejs20.x": "arn:aws:lambda:ap-northeast-1:464622532012:layer:Datadog-Node20-x:132",
      "nodejs22.x": "arn:aws:lambda:ap-northeast-1:464622532012:layer:Datadog-Node22-x:132",
      "nodejs24.x": "arn:aws:lambda:ap-northeast-1:464622532012:layer:Datadog-Node24-x:132",
      "python3.7": "arn:aws:lambda:ap-northeast-1:464622532012:layer:Datadog-Python37:85",
      "python3.8": "arn:aws:lambda:ap-northeast-1:464622532012:layer:Datadog-Python38:120",
      "python3.8-arm": "arn:aws:lambda:ap-northeast-1:464622532012:layer:Datadog-Python38-ARM:120",
      "python3.9": "arn:aws:lambda:ap-northeast-1:464622532012:layer:Datadog-Python39:120",
      "python3.9-arm": "arn:aws:lambda:ap-northeast-1:464622532012:layer:Datadog-Python39-ARM:120",
      "python3.10": "arn:aws:lambda:ap-northeast-1:464622532012:layer:Datadog-Python310:120",
      "python3.10-arm": "arn:aws:lambda:ap-northeast-1:464622532012:layer:Datadog-Python310-ARM:120",
      "python3.11": "arn:aws:lambda:ap-northeast-1:464622532012:layer:Datadog-Python311:120",
      "python3.11-arm": "arn:aws:lambda:ap-northeast-1:464622532012:layer:Datadog-Python311-ARM:120",
      "python3.12": "arn:aws:lambda:ap-northeast-1:464622532012:layer:Datadog-Python312:120",
      "python3.12-arm": "arn:aws:lambda:ap-northeast-1:464622532012:layer:Datadog-Python312-ARM:120",
      "python3.13": "arn:aws:lambda:ap-northeast-1:464622532012:layer:Datadog-Python313:120",
      "python3.13-arm": "arn:aws:lambda:ap-northeast-1:464622532012:layer:Datadog-Python313-ARM:120",
      "python3.14": "arn:aws:lambda:ap-northeast-1:464622532012:layer:Datadog-Python314:120",
      "python3.14-arm": "arn:aws:lambda:ap-northeast-1:464622532012:layer:Datadog-Python314-ARM:120",
      "ruby3.2": "arn:aws:lambda:ap-northeast-1:464622532012:layer:Datadog-Ruby3-2:27",
      "ruby3.2-arm": "arn:aws:lambda:ap-northeast-1:464622532012:layer:Datadog-Ruby3-2-ARM:27",
      "ruby3.3": "arn:aws:lambda:ap-northeast-1:464622532012:layer:Datadog-Ruby3-3:27",
      "ruby3.3-arm": "arn:aws:lambda:ap-northeast-1:464622532012:layer:Datadog-Ruby3-3-ARM:27",
      "ruby3.4": "arn:aws:lambda:ap-northeast-1:464622532012:layer:Datadog-Ruby3-4:27",
      "ruby3.4-arm": "arn:aws:lambda:ap-northeast-1:464622532012:layer:Datadog-Ruby3-4-ARM:27",
      "extension": "arn:aws:lambda:ap-northeast-1:464622532012:layer:Datadog-Extension:91",
      "extension-arm": "arn:aws:lambda:ap-northeast-1:464622532012:layer:Datadog-Extension-ARM:91",
      "extension-fips": "arn:aws:lambda:ap-northeast-1:464622532012:layer:Datadog-Extension-FIPS:91",
      "extension-arm-fips": "arn:aws:lambda:ap-northeast-1:464622532012:layer:Datadog-Extension-ARM-FIPS:91",
      "dotnet": "arn:aws:lambda:ap-northeast-1:464622532012:layer:dd-trace-dotnet:23",
      "dotnet-arm": "arn:aws:lambda:ap-northeast-1:464622532012:layer:dd-trace-dotnet-ARM:23",
      "java": "arn:aws:lambda:ap-northeast-1:464622532012:layer:dd-trace-java:25"
    },
    "sa-east-1": {
      "nodejs16.x": "arn:aws:lambda:sa-east-1:464622532012:layer:Datadog-Node16-x:120",
      "nodejs18.x": "arn:aws:lambda:sa-east-1:464622532012:layer:Datadog-Node18-x:132",
      "nodejs20.x": "arn:aws:lambda:sa-east-1:464622532012:layer:Datadog-Node20-x:132",
      "nodejs22.x": "arn:aws:lambda:sa-east-1:464622532012:layer:Datadog-Node22-x:132",
      "nodejs24.x": "arn:aws:lambda:sa-east-1:464622532012:layer:Datadog-Node24-x:132",
      "python3.7": "arn:aws:lambda:sa-east-1:464622532012:layer:Datadog-Python37:85",
      "python3.8": "arn:aws:lambda:sa-east-1:464622532012:layer:Datadog-Python38:120",
      "python3.8-arm": "arn:aws:lambda:sa-east-1:464622532012:layer:Datadog-Python38-ARM:120",
      "python3.9": "arn:aws:lambda:sa-east-1:464622532012:layer:Datadog-Python39:120",
      "python3.9-arm": "arn:aws:lambda:sa-east-1:464622532012:layer:Datadog-Python39-ARM:120",
      "python3.10": "arn:aws:lambda:sa-east-1:464622532012:layer:Datadog-Python310:120",
      "python3.10-arm": "arn:aws:lambda:sa-east-1:464622532012:layer:Datadog-Python310-ARM:120",
      "python3.11": "arn:aws:lambda:sa-east-1:464622532012:layer:Datadog-Python311:120",
      "python3.11-arm": "arn:aws:lambda:sa-east-1:464622532012:layer:Datadog-Python311-ARM:120",
      "python3.12": "arn:aws:lambda:sa-east-1:464622532012:layer:Datadog-Python312:120",
      "python3.12-arm": "arn:aws:lambda:sa-east-1:464622532012:layer:Datadog-Python312-ARM:120",
      "python3.13": "arn:aws:lambda:sa-east-1:464622532012:layer:Datadog-Python313:120",
      "python3.13-arm": "arn:aws:lambda:sa-east-1:464622532012:layer:Datadog-Python313-ARM:120",
      "python3.14": "arn:aws:lambda:sa-east-1:464622532012:layer:Datadog-Python314:120",
      "python3.14-arm": "arn:aws:lambda:sa-east-1:464622532012:layer:Datadog-Python314-ARM:120",
      "ruby3.2": "arn:aws:lambda:sa-east-1:464622532012:layer:Datadog-Ruby3-2:27",
      "ruby3.2-arm": "arn:aws:lambda:sa-east-1:464622532012:layer:Datadog-Ruby3-2-ARM:27",
      "ruby3.3": "arn:aws:lambda:sa-east-1:464622532012:layer:Datadog-Ruby3-3:27",
      "ruby3.3-arm": "arn:aws:lambda:sa-east-1:464622532012:layer:Datadog-Ruby3-3-ARM:27",
      "ruby3.4": "arn:aws:lambda:sa-east-1:464622532012:layer:Datadog-Ruby3-4:27",
      "ruby3.4-arm": "arn:aws:lambda:sa-east-1:464622532012:layer:Datadog-Ruby3-4-ARM:27",
      "extension": "arn:aws:lambda:sa-east-1:464622532012:layer:Datadog-Extension:91",
      "extension-arm": "arn:aws:lambda:sa-east-1:464622532012:layer:Datadog-Extension-ARM:91",
      "extension-fips": "arn:aws:lambda:sa-east-1:464622532012:layer:Datadog-Extension-FIPS:91",
      "extension-arm-fips": "arn:aws:lambda:sa-east-1:464622532012:layer:Datadog-Extension-ARM-FIPS:91",
      "dotnet": "arn:aws:lambda:sa-east-1:464622532012:layer:dd-trace-dotnet:23",
      "dotnet-arm": "arn:aws:lambda:sa-east-1:464622532012:layer:dd-trace-dotnet-ARM:23",
      "java": "arn:aws:lambda:sa-east-1:464622532012:layer:dd-trace-java:25"
    },
    "ap-east-1": {
      "nodejs16.x": "arn:aws:lambda:ap-east-1:464622532012:layer:Datadog-Node16-x:120",
      "nodejs18.x": "arn:aws:lambda:ap-east-1:464622532012:layer:Datadog-Node18-x:132",
      "nodejs20.x": "arn:aws:lambda:ap-east-1:464622532012:layer:Datadog-Node20-x:132",
      "nodejs22.x": "arn:aws:lambda:ap-east-1:464622532012:layer:Datadog-Node22-x:132",
      "nodejs24.x": "arn:aws:lambda:ap-east-1:464622532012:layer:Datadog-Node24-x:132",
      "python3.7": "arn:aws:lambda:ap-east-1:464622532012:layer:Datadog-Python37:85",
      "python3.8": "arn:aws:lambda:ap-east-1:464622532012:layer:Datadog-Python38:120",
      "python3.8-arm": "arn:aws:lambda:ap-east-1:464622532012:layer:Datadog-Python38-ARM:120",
      "python3.9": "arn:aws:lambda:ap-east-1:464622532012:layer:Datadog-Python39:120",
      "python3.9-arm": "arn:aws:lambda:ap-east-1:464622532012:layer:Datadog-Python39-ARM:120",
      "python3.10": "arn:aws:lambda:ap-east-1:464622532012:layer:Datadog-Python310:120",
      "python3.10-arm": "arn:aws:lambda:ap-east-1:464622532012:layer:Datadog-Python310-ARM:120",
      "python3.11": "arn:aws:lambda:ap-east-1:464622532012:layer:Datadog-Python311:120",
      "python3.11-arm": "arn:aws:lambda:ap-east-1:464622532012:layer:Datadog-Python311-ARM:120",
      "python3.12": "arn:aws:lambda:ap-east-1:464622532012:layer:Datadog-Python312:120",
      "python3.12-arm": "arn:aws:lambda:ap-east-1:464622532012:layer:Datadog-Python312-ARM:120",
      "python3.13": "arn:aws:lambda:ap-east-1:464622532012:layer:Datadog-Python313:120",
      "python3.13-arm": "arn:aws:lambda:ap-east-1:464622532012:layer:Datadog-Python313-ARM:120",
      "python3.14": "arn:aws:lambda:ap-east-1:464622532012:layer:Datadog-Python314:120",
      "python3.14-arm": "arn:aws:lambda:ap-east-1:464622532012:layer:Datadog-Python314-ARM:120",
      "ruby3.2": "arn:aws:lambda:ap-east-1:464622532012:layer:Datadog-Ruby3-2:27",
      "ruby3.2-arm": "arn:aws:lambda:ap-east-1:464622532012:layer:Datadog-Ruby3-2-ARM:27",
      "ruby3.3": "arn:aws:lambda:ap-east-1:464622532012:layer:Datadog-Ruby3-3:27",
      "ruby3.3-arm": "arn:aws:lambda:ap-east-1:464622532012:layer:Datadog-Ruby3-3-ARM:27",
      "ruby3.4": "arn:aws:lambda:ap-east-1:464622532012:layer:Datadog-Ruby3-4:27",
      "ruby3.4-arm": "arn:aws:lambda:ap-east-1:464622532012:layer:Datadog-Ruby3-4-ARM:27",
      "extension": "arn:aws:lambda:ap-east-1:464622532012:layer:Datadog-Extension:91",
      "extension-arm": "arn:aws:lambda:ap-east-1:464622532012:layer:Datadog-Extension-ARM:91",
      "extension-fips": "arn:aws:lambda:ap-east-1:464622532012:layer:Datadog-Extension-FIPS:91",
      "extension-arm-fips": "arn:aws:lambda:ap-east-1:464622532012:layer:Datadog-Extension-ARM-FIPS:91",
      "dotnet": "arn:aws:lambda:ap-east-1:464622532012:layer:dd-trace-dotnet:23",
      "dotnet-arm": "arn:aws:lambda:ap-east-1:464622532012:layer:dd-trace-dotnet-ARM:23",
      "java": "arn:aws:lambda:ap-east-1:464622532012:layer:dd-trace-java:25"
    },
    "ca-west-1": {
      "nodejs16.x": "arn:aws:lambda:ca-west-1:464622532012:layer:Datadog-Node16-x:120",
      "nodejs18.x": "arn:aws:lambda:ca-west-1:464622532012:layer:Datadog-Node18-x:132",
      "nodejs20.x": "arn:aws:lambda:ca-west-1:464622532012:layer:Datadog-Node20-x:132",
      "nodejs22.x": "arn:aws:lambda:ca-west-1:464622532012:layer:Datadog-Node22-x:132",
      "nodejs24.x": "arn:aws:lambda:ca-west-1:464622532012:layer:Datadog-Node24-x:132",
      "python3.8": "arn:aws:lambda:ca-west-1:464622532012:layer:Datadog-Python38:120",
      "python3.8-arm": "arn:aws:lambda:ca-west-1:464622532012:layer:Datadog-Python38-ARM:120",
      "python3.9": "arn:aws:lambda:ca-west-1:464622532012:layer:Datadog-Python39:120",
      "python3.9-arm": "arn:aws:lambda:ca-west-1:464622532012:layer:Datadog-Python39-ARM:120",
      "python3.10": "arn:aws:lambda:ca-west-1:464622532012:layer:Datadog-Python310:120",
      "python3.10-arm": "arn:aws:lambda:ca-west-1:464622532012:layer:Datadog-Python310-ARM:120",
      "python3.11": "arn:aws:lambda:ca-west-1:464622532012:layer:Datadog-Python311:120",
      "python3.11-arm": "arn:aws:lambda:ca-west-1:464622532012:layer:Datadog-Python311-ARM:120",
      "python3.12": "arn:aws:lambda:ca-west-1:464622532012:layer:Datadog-Python312:120",
      "python3.12-arm": "arn:aws:lambda:ca-west-1:464622532012:layer:Datadog-Python312-ARM:120",
      "python3.13": "arn:aws:lambda:ca-west-1:464622532012:layer:Datadog-Python313:120",
      "python3.13-arm": "arn:aws:lambda:ca-west-1:464622532012:layer:Datadog-Python313-ARM:120",
      "python3.14": "arn:aws:lambda:ca-west-1:464622532012:layer:Datadog-Python314:120",
      "python3.14-arm": "arn:aws:lambda:ca-west-1:464622532012:layer:Datadog-Python314-ARM:120",
      "ruby3.2": "arn:aws:lambda:ca-west-1:464622532012:layer:Datadog-Ruby3-2:27",
      "ruby3.2-arm": "arn:aws:lambda:ca-west-1:464622532012:layer:Datadog-Ruby3-2-ARM:27",
      "ruby3.3": "arn:aws:lambda:ca-west-1:464622532012:layer:Datadog-Ruby3-3:27",
      "ruby3.3-arm": "arn:aws:lambda:ca-west-1:464622532012:layer:Datadog-Ruby3-3-ARM:27",
      "ruby3.4": "arn:aws:lambda:ca-west-1:464622532012:layer:Datadog-Ruby3-4:27",
      "ruby3.4-arm": "arn:aws:lambda:ca-west-1:464622532012:layer:Datadog-Ruby3-4-ARM:27",
      "extension": "arn:aws:lambda:ca-west-1:464622532012:layer:Datadog-Extension:91",
      "extension-arm": "arn:aws:lambda:ca-west-1:464622532012:layer:Datadog-Extension-ARM:91",
      "extension-fips": "arn:aws:lambda:ca-west-1:464622532012:layer:Datadog-Extension-FIPS:91",
      "extension-arm-fips": "arn:aws:lambda:ca-west-1:464622532012:layer:Datadog-Extension-ARM-FIPS:91",
      "dotnet": "arn:aws:lambda:ca-west-1:464622532012:layer:dd-trace-dotnet:23",
      "dotnet-arm": "arn:aws:lambda:ca-west-1:464622532012:layer:dd-trace-dotnet-ARM:23",
      "java": "arn:aws:lambda:ca-west-1:464622532012:layer:dd-trace-java:25"
    },
    "ap-southeast-1": {
      "nodejs16.x": "arn:aws:lambda:ap-southeast-1:464622532012:layer:Datadog-Node16-x:120",
      "nodejs18.x": "arn:aws:lambda:ap-southeast-1:464622532012:layer:Datadog-Node18-x:132",
      "nodejs20.x": "arn:aws:lambda:ap-southeast-1:464622532012:layer:Datadog-Node20-x:132",
      "nodejs22.x": "arn:aws:lambda:ap-southeast-1:464622532012:layer:Datadog-Node22-x:132",
      "nodejs24.x": "arn:aws:lambda:ap-southeast-1:464622532012:layer:Datadog-Node24-x:132",
      "python3.7": "arn:aws:lambda:ap-southeast-1:464622532012:layer:Datadog-Python37:85",
      "python3.8": "arn:aws:lambda:ap-southeast-1:464622532012:layer:Datadog-Python38:120",
      "python3.8-arm": "arn:aws:lambda:ap-southeast-1:464622532012:layer:Datadog-Python38-ARM:120",
      "python3.9": "arn:aws:lambda:ap-southeast-1:464622532012:layer:Datadog-Python39:120",
      "python3.9-arm": "arn:aws:lambda:ap-southeast-1:464622532012:layer:Datadog-Python39-ARM:120",
      "python3.10": "arn:aws:lambda:ap-southeast-1:464622532012:layer:Datadog-Python310:120",
      "python3.10-arm": "arn:aws:lambda:ap-southeast-1:464622532012:layer:Datadog-Python310-ARM:120",
      "python3.11": "arn:aws:lambda:ap-southeast-1:464622532012:layer:Datadog-Python311:120",
      "python3.11-arm": "arn:aws:lambda:ap-southeast-1:464622532012:layer:Datadog-Python311-ARM:120",
      "python3.12": "arn:aws:lambda:ap-southeast-1:464622532012:layer:Datadog-Python312:120",
      "python3.12-arm": "arn:aws:lambda:ap-southeast-1:464622532012:layer:Datadog-Python312-ARM:120",
      "python3.13": "arn:aws:lambda:ap-southeast-1:464622532012:layer:Datadog-Python313:120",
      "python3.13-arm": "arn:aws:lambda:ap-southeast-1:464622532012:layer:Datadog-Python313-ARM:120",
      "python3.14": "arn:aws:lambda:ap-southeast-1:464622532012:layer:Datadog-Python314:120",
      "python3.14-arm": "arn:aws:lambda:ap-southeast-1:464622532012:layer:Datadog-Python314-ARM:120",
      "ruby3.2": "arn:aws:lambda:ap-southeast-1:464622532012:layer:Datadog-Ruby3-2:27",
      "ruby3.2-arm": "arn:aws:lambda:ap-southeast-1:464622532012:layer:Datadog-Ruby3-2-ARM:27",
      "ruby3.3": "arn:aws:lambda:ap-southeast-1:464622532012:layer:Datadog-Ruby3-3:27",
      "ruby3.3-arm": "arn:aws:lambda:ap-southeast-1:464622532012:layer:Datadog-Ruby3-3-ARM:27",
      "ruby3.4": "arn:aws:lambda:ap-southeast-1:464622532012:layer:Datadog-Ruby3-4:27",
      "ruby3.4-arm": "arn:aws:lambda:ap-southeast-1:464622532012:layer:Datadog-Ruby3-4-ARM:27",
      "extension": "arn:aws:lambda:ap-southeast-1:464622532012:layer:Datadog-Extension:91",
      "extension-arm": "arn:aws:lambda:ap-southeast-1:464622532012:layer:Datadog-Extension-ARM:91",
      "extension-fips": "arn:aws:lambda:ap-southeast-1:464622532012:layer:Datadog-Extension-FIPS:91",
      "extension-arm-fips": "arn:aws:lambda:ap-southeast-1:464622532012:layer:Datadog-Extension-ARM-FIPS:91",
      "dotnet": "arn:aws:lambda:ap-southeast-1:464622532012:layer:dd-trace-dotnet:23",
      "dotnet-arm": "arn:aws:lambda:ap-southeast-1:464622532012:layer:dd-trace-dotnet-ARM:23",
      "java": "arn:aws:lambda:ap-southeast-1:464622532012:layer:dd-trace-java:25"
    },
    "ap-southeast-2": {
      "nodejs16.x": "arn:aws:lambda:ap-southeast-2:464622532012:layer:Datadog-Node16-x:120",
      "nodejs18.x": "arn:aws:lambda:ap-southeast-2:464622532012:layer:Datadog-Node18-x:132",
      "nodejs20.x": "arn:aws:lambda:ap-southeast-2:464622532012:layer:Datadog-Node20-x:132",
      "nodejs22.x": "arn:aws:lambda:ap-southeast-2:464622532012:layer:Datadog-Node22-x:132",
      "nodejs24.x": "arn:aws:lambda:ap-southeast-2:464622532012:layer:Datadog-Node24-x:132",
      "python3.7": "arn:aws:lambda:ap-southeast-2:464622532012:layer:Datadog-Python37:85",
      "python3.8": "arn:aws:lambda:ap-southeast-2:464622532012:layer:Datadog-Python38:120",
      "python3.8-arm": "arn:aws:lambda:ap-southeast-2:464622532012:layer:Datadog-Python38-ARM:120",
      "python3.9": "arn:aws:lambda:ap-southeast-2:464622532012:layer:Datadog-Python39:120",
      "python3.9-arm": "arn:aws:lambda:ap-southeast-2:464622532012:layer:Datadog-Python39-ARM:120",
      "python3.10": "arn:aws:lambda:ap-southeast-2:464622532012:layer:Datadog-Python310:120",
      "python3.10-arm": "arn:aws:lambda:ap-southeast-2:464622532012:layer:Datadog-Python310-ARM:120",
      "python3.11": "arn:aws:lambda:ap-southeast-2:464622532012:layer:Datadog-Python311:120",
      "python3.11-arm": "arn:aws:lambda:ap-southeast-2:464622532012:layer:Datadog-Python311-ARM:120",
      "python3.12": "arn:aws:lambda:ap-southeast-2:464622532012:layer:Datadog-Python312:120",
      "python3.12-arm": "arn:aws:lambda:ap-southeast-2:464622532012:layer:Datadog-Python312-ARM:120",
      "python3.13": "arn:aws:lambda:ap-southeast-2:464622532012:layer:Datadog-Python313:120",
      "python3.13-arm": "arn:aws:lambda:ap-southeast-2:464622532012:layer:Datadog-Python313-ARM:120",
      "python3.14": "arn:aws:lambda:ap-southeast-2:464622532012:layer:Datadog-Python314:120",
      "python3.14-arm": "arn:aws:lambda:ap-southeast-2:464622532012:layer:Datadog-Python314-ARM:120",
      "ruby3.2": "arn:aws:lambda:ap-southeast-2:464622532012:layer:Datadog-Ruby3-2:27",
      "ruby3.2-arm": "arn:aws:lambda:ap-southeast-2:464622532012:layer:Datadog-Ruby3-2-ARM:27",
      "ruby3.3": "arn:aws:lambda:ap-southeast-2:464622532012:layer:Datadog-Ruby3-3:27",
      "ruby3.3-arm": "arn:aws:lambda:ap-southeast-2:464622532012:layer:Datadog-Ruby3-3-ARM:27",
      "ruby3.4": "arn:aws:lambda:ap-southeast-2:464622532012:layer:Datadog-Ruby3-4:27",
      "ruby3.4-arm": "arn:aws:lambda:ap-southeast-2:464622532012:layer:Datadog-Ruby3-4-ARM:27",
      "extension": "arn:aws:lambda:ap-southeast-2:464622532012:layer:Datadog-Extension:91",
      "extension-arm": "arn:aws:lambda:ap-southeast-2:464622532012:layer:Datadog-Extension-ARM:91",
      "extension-fips": "arn:aws:lambda:ap-southeast-2:464622532012:layer:Datadog-Extension-FIPS:91",
      "extension-arm-fips": "arn:aws:lambda:ap-southeast-2:464622532012:layer:Datadog-Extension-ARM-FIPS:91",
      "dotnet": "arn:aws:lambda:ap-southeast-2:464622532012:layer:dd-trace-dotnet:23",
      "dotnet-arm": "arn:aws:lambda:ap-southeast-2:464622532012:layer:dd-trace-dotnet-ARM:23",
      "java": "arn:aws:lambda:ap-southeast-2:464622532012:layer:dd-trace-java:25"
    },
    "ap-southeast-3": {
      "nodejs16.x": "arn:aws:lambda:ap-southeast-3:464622532012:layer:Datadog-Node16-x:120",
      "nodejs18.x": "arn:aws:lambda:ap-southeast-3:464622532012:layer:Datadog-Node18-x:132",
      "nodejs20.x": "arn:aws:lambda:ap-southeast-3:464622532012:layer:Datadog-Node20-x:132",
      "nodejs22.x": "arn:aws:lambda:ap-southeast-3:464622532012:layer:Datadog-Node22-x:132",
      "nodejs24.x": "arn:aws:lambda:ap-southeast-3:464622532012:layer:Datadog-Node24-x:132",
      "python3.7": "arn:aws:lambda:ap-southeast-3:464622532012:layer:Datadog-Python37:85",
      "python3.8": "arn:aws:lambda:ap-southeast-3:464622532012:layer:Datadog-Python38:120",
      "python3.8-arm": "arn:aws:lambda:ap-southeast-3:464622532012:layer:Datadog-Python38-ARM:120",
      "python3.9": "arn:aws:lambda:ap-southeast-3:464622532012:layer:Datadog-Python39:120",
      "python3.9-arm": "arn:aws:lambda:ap-southeast-3:464622532012:layer:Datadog-Python39-ARM:120",
      "python3.10": "arn:aws:lambda:ap-southeast-3:464622532012:layer:Datadog-Python310:120",
      "python3.10-arm": "arn:aws:lambda:ap-southeast-3:464622532012:layer:Datadog-Python310-ARM:120",
      "python3.11": "arn:aws:lambda:ap-southeast-3:464622532012:layer:Datadog-Python311:120",
      "python3.11-arm": "arn:aws:lambda:ap-southeast-3:464622532012:layer:Datadog-Python311-ARM:120",
      "python3.12": "arn:aws:lambda:ap-southeast-3:464622532012:layer:Datadog-Python312:120",
      "python3.12-arm": "arn:aws:lambda:ap-southeast-3:464622532012:layer:Datadog-Python312-ARM:120",
      "python3.13": "arn:aws:lambda:ap-southeast-3:464622532012:layer:Datadog-Python313:120",
      "python3.13-arm": "arn:aws:lambda:ap-southeast-3:464622532012:layer:Datadog-Python313-ARM:120",
      "python3.14": "arn:aws:lambda:ap-southeast-3:464622532012:layer:Datadog-Python314:120",
      "python3.14-arm": "arn:aws:lambda:ap-southeast-3:464622532012:layer:Datadog-Python314-ARM:120",
      "ruby3.2": "arn:aws:lambda:ap-southeast-3:464622532012:layer:Datadog-Ruby3-2:27",
      "ruby3.2-arm": "arn:aws:lambda:ap-southeast-3:464622532012:layer:Datadog-Ruby3-2-ARM:27",
      "ruby3.3": "arn:aws:lambda:ap-southeast-3:464622532012:layer:Datadog-Ruby3-3:27",
      "ruby3.3-arm": "arn:aws:lambda:ap-southeast-3:464622532012:layer:Datadog-Ruby3-3-ARM:27",
      "ruby3.4": "arn:aws:lambda:ap-southeast-3:464622532012:layer:Datadog-Ruby3-4:27",
      "ruby3.4-arm": "arn:aws:lambda:ap-southeast-3:464622532012:layer:Datadog-Ruby3-4-ARM:27",
      "extension": "arn:aws:lambda:ap-southeast-3:464622532012:layer:Datadog-Extension:91",
      "extension-arm": "arn:aws:lambda:ap-southeast-3:464622532012:layer:Datadog-Extension-ARM:91",
      "extension-fips": "arn:aws:lambda:ap-southeast-3:464622532012:layer:Datadog-Extension-FIPS:91",
      "extension-arm-fips": "arn:aws:lambda:ap-southeast-3:464622532012:layer:Datadog-Extension-ARM-FIPS:91",
      "dotnet": "arn:aws:lambda:ap-southeast-3:464622532012:layer:dd-trace-dotnet:23",
      "dotnet-arm": "arn:aws:lambda:ap-southeast-3:464622532012:layer:dd-trace-dotnet-ARM:23",
      "java": "arn:aws:lambda:ap-southeast-3:464622532012:layer:dd-trace-java:25"
    },
    "ap-southeast-4": {
      "nodejs16.x": "arn:aws:lambda:ap-southeast-4:464622532012:layer:Datadog-Node16-x:120",
      "nodejs18.x": "arn:aws:lambda:ap-southeast-4:464622532012:layer:Datadog-Node18-x:132",
      "nodejs20.x": "arn:aws:lambda:ap-southeast-4:464622532012:layer:Datadog-Node20-x:132",
      "nodejs22.x": "arn:aws:lambda:ap-southeast-4:464622532012:layer:Datadog-Node22-x:132",
      "nodejs24.x": "arn:aws:lambda:ap-southeast-4:464622532012:layer:Datadog-Node24-x:132",
      "python3.7": "arn:aws:lambda:ap-southeast-4:464622532012:layer:Datadog-Python37:85",
      "python3.8": "arn:aws:lambda:ap-southeast-4:464622532012:layer:Datadog-Python38:120",
      "python3.8-arm": "arn:aws:lambda:ap-southeast-4:464622532012:layer:Datadog-Python38-ARM:120",
      "python3.9": "arn:aws:lambda:ap-southeast-4:464622532012:layer:Datadog-Python39:120",
      "python3.9-arm": "arn:aws:lambda:ap-southeast-4:464622532012:layer:Datadog-Python39-ARM:120",
      "python3.10": "arn:aws:lambda:ap-southeast-4:464622532012:layer:Datadog-Python310:120",
      "python3.10-arm": "arn:aws:lambda:ap-southeast-4:464622532012:layer:Datadog-Python310-ARM:120",
      "python3.11": "arn:aws:lambda:ap-southeast-4:464622532012:layer:Datadog-Python311:120",
      "python3.11-arm": "arn:aws:lambda:ap-southeast-4:464622532012:layer:Datadog-Python311-ARM:120",
      "python3.12": "arn:aws:lambda:ap-southeast-4:464622532012:layer:Datadog-Python312:120",
      "python3.12-arm": "arn:aws:lambda:ap-southeast-4:464622532012:layer:Datadog-Python312-ARM:120",
      "python3.13": "arn:aws:lambda:ap-southeast-4:464622532012:layer:Datadog-Python313:120",
      "python3.13-arm": "arn:aws:lambda:ap-southeast-4:464622532012:layer:Datadog-Python313-ARM:120",
      "python3.14": "arn:aws:lambda:ap-southeast-4:464622532012:layer:Datadog-Python314:120",
      "python3.14-arm": "arn:aws:lambda:ap-southeast-4:464622532012:layer:Datadog-Python314-ARM:120",
      "ruby3.2": "arn:aws:lambda:ap-southeast-4:464622532012:layer:Datadog-Ruby3-2:27",
      "ruby3.2-arm": "arn:aws:lambda:ap-southeast-4:464622532012:layer:Datadog-Ruby3-2-ARM:27",
      "ruby3.3": "arn:aws:lambda:ap-southeast-4:464622532012:layer:Datadog-Ruby3-3:27",
      "ruby3.3-arm": "arn:aws:lambda:ap-southeast-4:464622532012:layer:Datadog-Ruby3-3-ARM:27",
      "ruby3.4": "arn:aws:lambda:ap-southeast-4:464622532012:layer:Datadog-Ruby3-4:27",
      "ruby3.4-arm": "arn:aws:lambda:ap-southeast-4:464622532012:layer:Datadog-Ruby3-4-ARM:27",
      "extension": "arn:aws:lambda:ap-southeast-4:464622532012:layer:Datadog-Extension:91",
      "extension-arm": "arn:aws:lambda:ap-southeast-4:464622532012:layer:Datadog-Extension-ARM:91",
      "extension-fips": "arn:aws:lambda:ap-southeast-4:464622532012:layer:Datadog-Extension-FIPS:91",
      "extension-arm-fips": "arn:aws:lambda:ap-southeast-4:464622532012:layer:Datadog-Extension-ARM-FIPS:91",
      "dotnet": "arn:aws:lambda:ap-southeast-4:464622532012:layer:dd-trace-dotnet:23",
      "dotnet-arm": "arn:aws:lambda:ap-southeast-4:464622532012:layer:dd-trace-dotnet-ARM:23",
      "java": "arn:aws:lambda:ap-southeast-4:464622532012:layer:dd-trace-java:25"
    },
    "us-east-1": {
      "nodejs16.x": "arn:aws:lambda:us-east-1:464622532012:layer:Datadog-Node16-x:120",
      "nodejs18.x": "arn:aws:lambda:us-east-1:464622532012:layer:Datadog-Node18-x:132",
      "nodejs20.x": "arn:aws:lambda:us-east-1:464622532012:layer:Datadog-Node20-x:132",
      "nodejs22.x": "arn:aws:lambda:us-east-1:464622532012:layer:Datadog-Node22-x:132",
      "nodejs24.x": "arn:aws:lambda:us-east-1:464622532012:layer:Datadog-Node24-x:132",
      "python3.7": "arn:aws:lambda:us-east-1:464622532012:layer:Datadog-Python37:85",
      "python3.8": "arn:aws:lambda:us-east-1:464622532012:layer:Datadog-Python38:120",
      "python3.8-arm": "arn:aws:lambda:us-east-1:464622532012:layer:Datadog-Python38-ARM:120",
      "python3.9": "arn:aws:lambda:us-east-1:464622532012:layer:Datadog-Python39:120",
      "python3.9-arm": "arn:aws:lambda:us-east-1:464622532012:layer:Datadog-Python39-ARM:120",
      "python3.10": "arn:aws:lambda:us-east-1:464622532012:layer:Datadog-Python310:120",
      "python3.10-arm": "arn:aws:lambda:us-east-1:464622532012:layer:Datadog-Python310-ARM:120",
      "python3.11": "arn:aws:lambda:us-east-1:464622532012:layer:Datadog-Python311:120",
      "python3.11-arm": "arn:aws:lambda:us-east-1:464622532012:layer:Datadog-Python311-ARM:120",
      "python3.12": "arn:aws:lambda:us-east-1:464622532012:layer:Datadog-Python312:120",
      "python3.12-arm": "arn:aws:lambda:us-east-1:464622532012:layer:Datadog-Python312-ARM:120",
      "python3.13": "arn:aws:lambda:us-east-1:464622532012:layer:Datadog-Python313:120",
      "python3.13-arm": "arn:aws:lambda:us-east-1:464622532012:layer:Datadog-Python313-ARM:120",
      "python3.14": "arn:aws:lambda:us-east-1:464622532012:layer:Datadog-Python314:120",
      "python3.14-arm": "arn:aws:lambda:us-east-1:464622532012:layer:Datadog-Python314-ARM:120",
      "ruby3.2": "arn:aws:lambda:us-east-1:464622532012:layer:Datadog-Ruby3-2:27",
      "ruby3.2-arm": "arn:aws:lambda:us-east-1:464622532012:layer:Datadog-Ruby3-2-ARM:27",
      "ruby3.3": "arn:aws:lambda:us-east-1:464622532012:layer:Datadog-Ruby3-3:27",
      "ruby3.3-arm": "arn:aws:lambda:us-east-1:464622532012:layer:Datadog-Ruby3-3-ARM:27",
      "ruby3.4": "arn:aws:lambda:us-east-1:464622532012:layer:Datadog-Ruby3-4:27",
      "ruby3.4-arm": "arn:aws:lambda:us-east-1:464622532012:layer:Datadog-Ruby3-4-ARM:27",
      "extension": "arn:aws:lambda:us-east-1:464622532012:layer:Datadog-Extension:91",
      "extension-arm": "arn:aws:lambda:us-east-1:464622532012:layer:Datadog-Extension-ARM:91",
      "extension-fips": "arn:aws:lambda:us-east-1:464622532012:layer:Datadog-Extension-FIPS:91",
      "extension-arm-fips": "arn:aws:lambda:us-east-1:464622532012:layer:Datadog-Extension-ARM-FIPS:91",
      "dotnet": "arn:aws:lambda:us-east-1:464622532012:layer:dd-trace-dotnet:23",
      "dotnet-arm": "arn:aws:lambda:us-east-1:464622532012:layer:dd-trace-dotnet-ARM:23",
      "java": "arn:aws:lambda:us-east-1:464622532012:layer:dd-trace-java:25"
    },
    "ap-southeast-5": {
      "nodejs16.x": "arn:aws:lambda:ap-southeast-5:464622532012:layer:Datadog-Node16-x:120",
      "nodejs18.x": "arn:aws:lambda:ap-southeast-5:464622532012:layer:Datadog-Node18-x:132",
      "nodejs20.x": "arn:aws:lambda:ap-southeast-5:464622532012:layer:Datadog-Node20-x:132",
      "nodejs22.x": "arn:aws:lambda:ap-southeast-5:464622532012:layer:Datadog-Node22-x:132",
      "nodejs24.x": "arn:aws:lambda:ap-southeast-5:464622532012:layer:Datadog-Node24-x:132",
      "python3.8": "arn:aws:lambda:ap-southeast-5:464622532012:layer:Datadog-Python38:120",
      "python3.8-arm": "arn:aws:lambda:ap-southeast-5:464622532012:layer:Datadog-Python38-ARM:120",
      "python3.9": "arn:aws:lambda:ap-southeast-5:464622532012:layer:Datadog-Python39:120",
      "python3.9-arm": "arn:aws:lambda:ap-southeast-5:464622532012:layer:Datadog-Python39-ARM:120",
      "python3.10": "arn:aws:lambda:ap-southeast-5:464622532012:layer:Datadog-Python310:120",
      "python3.10-arm": "arn:aws:lambda:ap-southeast-5:464622532012:layer:Datadog-Python310-ARM:120",
      "python3.11": "arn:aws:lambda:ap-southeast-5:464622532012:layer:Datadog-Python311:120",
      "python3.11-arm": "arn:aws:lambda:ap-southeast-5:464622532012:layer:Datadog-Python311-ARM:120",
      "python3.12": "arn:aws:lambda:ap-southeast-5:464622532012:layer:Datadog-Python312:120",
      "python3.12-arm": "arn:aws:lambda:ap-southeast-5:464622532012:layer:Datadog-Python312-ARM:120",
      "python3.13": "arn:aws:lambda:ap-southeast-5:464622532012:layer:Datadog-Python313:120",
      "python3.13-arm": "arn:aws:lambda:ap-southeast-5:464622532012:layer:Datadog-Python313-ARM:120",
      "python3.14": "arn:aws:lambda:ap-southeast-5:464622532012:layer:Datadog-Python314:120",
      "python3.14-arm": "arn:aws:lambda:ap-southeast-5:464622532012:layer:Datadog-Python314-ARM:120",
      "ruby3.2": "arn:aws:lambda:ap-southeast-5:464622532012:layer:Datadog-Ruby3-2:27",
      "ruby3.2-arm": "arn:aws:lambda:ap-southeast-5:464622532012:layer:Datadog-Ruby3-2-ARM:27",
      "ruby3.3": "arn:aws:lambda:ap-southeast-5:464622532012:layer:Datadog-Ruby3-3:27",
      "ruby3.3-arm": "arn:aws:lambda:ap-southeast-5:464622532012:layer:Datadog-Ruby3-3-ARM:27",
      "ruby3.4": "arn:aws:lambda:ap-southeast-5:464622532012:layer:Datadog-Ruby3-4:27",
      "ruby3.4-arm": "arn:aws:lambda:ap-southeast-5:464622532012:layer:Datadog-Ruby3-4-ARM:27",
      "extension": "arn:aws:lambda:ap-southeast-5:464622532012:layer:Datadog-Extension:91",
      "extension-arm": "arn:aws:lambda:ap-southeast-5:464622532012:layer:Datadog-Extension-ARM:91",
      "extension-fips": "arn:aws:lambda:ap-southeast-5:464622532012:layer:Datadog-Extension-FIPS:91",
      "extension-arm-fips": "arn:aws:lambda:ap-southeast-5:464622532012:layer:Datadog-Extension-ARM-FIPS:91",
      "dotnet": "arn:aws:lambda:ap-southeast-5:464622532012:layer:dd-trace-dotnet:23",
      "dotnet-arm": "arn:aws:lambda:ap-southeast-5:464622532012:layer:dd-trace-dotnet-ARM:23",
      "java": "arn:aws:lambda:ap-southeast-5:464622532012:layer:dd-trace-java:25"
    },
    "us-east-2": {
      "nodejs16.x": "arn:aws:lambda:us-east-2:464622532012:layer:Datadog-Node16-x:120",
      "nodejs18.x": "arn:aws:lambda:us-east-2:464622532012:layer:Datadog-Node18-x:132",
      "nodejs20.x": "arn:aws:lambda:us-east-2:464622532012:layer:Datadog-Node20-x:132",
      "nodejs22.x": "arn:aws:lambda:us-east-2:464622532012:layer:Datadog-Node22-x:132",
      "nodejs24.x": "arn:aws:lambda:us-east-2:464622532012:layer:Datadog-Node24-x:132",
      "python3.7": "arn:aws:lambda:us-east-2:464622532012:layer:Datadog-Python37:85",
      "python3.8": "arn:aws:lambda:us-east-2:464622532012:layer:Datadog-Python38:120",
      "python3.8-arm": "arn:aws:lambda:us-east-2:464622532012:layer:Datadog-Python38-ARM:120",
      "python3.9": "arn:aws:lambda:us-east-2:464622532012:layer:Datadog-Python39:120",
      "python3.9-arm": "arn:aws:lambda:us-east-2:464622532012:layer:Datadog-Python39-ARM:120",
      "python3.10": "arn:aws:lambda:us-east-2:464622532012:layer:Datadog-Python310:120",
      "python3.10-arm": "arn:aws:lambda:us-east-2:464622532012:layer:Datadog-Python310-ARM:120",
      "python3.11": "arn:aws:lambda:us-east-2:464622532012:layer:Datadog-Python311:120",
      "python3.11-arm": "arn:aws:lambda:us-east-2:464622532012:layer:Datadog-Python311-ARM:120",
      "python3.12": "arn:aws:lambda:us-east-2:464622532012:layer:Datadog-Python312:120",
      "python3.12-arm": "arn:aws:lambda:us-east-2:464622532012:layer:Datadog-Python312-ARM:120",
      "python3.13": "arn:aws:lambda:us-east-2:464622532012:layer:Datadog-Python313:120",
      "python3.13-arm": "arn:aws:lambda:us-east-2:464622532012:layer:Datadog-Python313-ARM:120",
      "python3.14": "arn:aws:lambda:us-east-2:464622532012:layer:Datadog-Python314:120",
      "python3.14-arm": "arn:aws:lambda:us-east-2:464622532012:layer:Datadog-Python314-ARM:120",
      "ruby3.2": "arn:aws:lambda:us-east-2:464622532012:layer:Datadog-Ruby3-2:27",
      "ruby3.2-arm": "arn:aws:lambda:us-east-2:464622532012:layer:Datadog-Ruby3-2-ARM:27",
      "ruby3.3": "arn:aws:lambda:us-east-2:464622532012:layer:Datadog-Ruby3-3:27",
      "ruby3.3-arm": "arn:aws:lambda:us-east-2:464622532012:layer:Datadog-Ruby3-3-ARM:27",
      "ruby3.4": "arn:aws:lambda:us-east-2:464622532012:layer:Datadog-Ruby3-4:27",
      "ruby3.4-arm": "arn:aws:lambda:us-east-2:464622532012:layer:Datadog-Ruby3-4-ARM:27",
      "extension": "arn:aws:lambda:us-east-2:464622532012:layer:Datadog-Extension:91",
      "extension-arm": "arn:aws:lambda:us-east-2:464622532012:layer:Datadog-Extension-ARM:91",
      "extension-fips": "arn:aws:lambda:us-east-2:464622532012:layer:Datadog-Extension-FIPS:91",
      "extension-arm-fips": "arn:aws:lambda:us-east-2:464622532012:layer:Datadog-Extension-ARM-FIPS:91",
      "dotnet": "arn:aws:lambda:us-east-2:464622532012:layer:dd-trace-dotnet:23",
      "dotnet-arm": "arn:aws:lambda:us-east-2:464622532012:layer:dd-trace-dotnet-ARM:23",
      "java": "arn:aws:lambda:us-east-2:464622532012:layer:dd-trace-java:25"
    },
    "ap-southeast-7": {
      "nodejs18.x": "arn:aws:lambda:ap-southeast-7:464622532012:layer:Datadog-Node18-x:132",
      "nodejs20.x": "arn:aws:lambda:ap-southeast-7:464622532012:layer:Datadog-Node20-x:132",
      "nodejs22.x": "arn:aws:lambda:ap-southeast-7:464622532012:layer:Datadog-Node22-x:132",
      "nodejs24.x": "arn:aws:lambda:ap-southeast-7:464622532012:layer:Datadog-Node24-x:132",
      "python3.8": "arn:aws:lambda:ap-southeast-7:464622532012:layer:Datadog-Python38:120",
      "python3.8-arm": "arn:aws:lambda:ap-southeast-7:464622532012:layer:Datadog-Python38-ARM:120",
      "python3.9": "arn:aws:lambda:ap-southeast-7:464622532012:layer:Datadog-Python39:120",
      "python3.9-arm": "arn:aws:lambda:ap-southeast-7:464622532012:layer:Datadog-Python39-ARM:120",
      "python3.10": "arn:aws:lambda:ap-southeast-7:464622532012:layer:Datadog-Python310:120",
      "python3.10-arm": "arn:aws:lambda:ap-southeast-7:464622532012:layer:Datadog-Python310-ARM:120",
      "python3.11": "arn:aws:lambda:ap-southeast-7:464622532012:layer:Datadog-Python311:120",
      "python3.11-arm": "arn:aws:lambda:ap-southeast-7:464622532012:layer:Datadog-Python311-ARM:120",
      "python3.12": "arn:aws:lambda:ap-southeast-7:464622532012:layer:Datadog-Python312:120",
      "python3.12-arm": "arn:aws:lambda:ap-southeast-7:464622532012:layer:Datadog-Python312-ARM:120",
      "python3.13": "arn:aws:lambda:ap-southeast-7:464622532012:layer:Datadog-Python313:120",
      "python3.13-arm": "arn:aws:lambda:ap-southeast-7:464622532012:layer:Datadog-Python313-ARM:120",
      "python3.14": "arn:aws:lambda:ap-southeast-7:464622532012:layer:Datadog-Python314:120",
      "python3.14-arm": "arn:aws:lambda:ap-southeast-7:464622532012:layer:Datadog-Python314-ARM:120",
      "ruby3.2": "arn:aws:lambda:ap-southeast-7:464622532012:layer:Datadog-Ruby3-2:27",
      "ruby3.2-arm": "arn:aws:lambda:ap-southeast-7:464622532012:layer:Datadog-Ruby3-2-ARM:27",
      "ruby3.3": "arn:aws:lambda:ap-southeast-7:464622532012:layer:Datadog-Ruby3-3:27",
      "ruby3.3-arm": "arn:aws:lambda:ap-southeast-7:464622532012:layer:Datadog-Ruby3-3-ARM:27",
      "ruby3.4": "arn:aws:lambda:ap-southeast-7:464622532012:layer:Datadog-Ruby3-4:27",
      "ruby3.4-arm": "arn:aws:lambda:ap-southeast-7:464622532012:layer:Datadog-Ruby3-4-ARM:27",
      "extension": "arn:aws:lambda:ap-southeast-7:464622532012:layer:Datadog-Extension:91",
      "extension-arm": "arn:aws:lambda:ap-southeast-7:464622532012:layer:Datadog-Extension-ARM:91",
      "extension-fips": "arn:aws:lambda:ap-southeast-7:464622532012:layer:Datadog-Extension-FIPS:91",
      "extension-arm-fips": "arn:aws:lambda:ap-southeast-7:464622532012:layer:Datadog-Extension-ARM-FIPS:91",
      "dotnet": "arn:aws:lambda:ap-southeast-7:464622532012:layer:dd-trace-dotnet:23",
      "dotnet-arm": "arn:aws:lambda:ap-southeast-7:464622532012:layer:dd-trace-dotnet-ARM:23",
      "java": "arn:aws:lambda:ap-southeast-7:464622532012:layer:dd-trace-java:25"
    }
  }
}
